Workbook

Sheet 2026
A1: Spalte1 | B1: Wörter | C1: Zeit | D1: Von | E1: Sprache | F1: Übersetzung | G1: Korrektur | H1: Kanal | I1: Eingang | J1: Lieferdatum | K1: Deadline | L1: Abteilung | M1: Status | N1: Verantwortlich | O1: Ablageort | P1: Bereich
A2: 2026-02-03T14-17-44_PM-History-Texts.xml | D2: TJa | E2: DE | G2: Franziska | H2: LS-Tracker | I2: 45993 | J2: 46026 | K2: 46056 | L2: =IF(_xlfn.XLOOKUP(D2, ABZ!A:A, ABZ!B:B, "", 0) = 0, "", _xlfn.XLOOKUP(D2, ABZ!A:A, ABZ!B:B, "", 0)) -> Product Management | M2: geliefert | N2: FSc | O2: Z:\Produkte\F!Box allgemein\Info.txt\Release\25_Smart24-P2\2026.02 | P2: Vertrieb
A3: 2026-02-03T15-55-13_PM-History-Texts_korr-de.xml | D3: TJa | E3: EN | F3: Franziska | H3: LS-Tracker | I3: 45691 | J3: 46056 | K3: 46056 | L3: =IF(_xlfn.XLOOKUP(D3, ABZ!A:A, ABZ!B:B, "", 0) = 0, "", _xlfn.XLOOKUP(D3, ABZ!A:A, ABZ!B:B, "", 0)) -> Product Management | M3: geliefert | O3: Z:\Produkte\F!Box allgemein\Info.txt\Release\25_Smart24-P2\2026.02 | P3: Vertrieb
A4: 2026_Ankuendigung_FRITZ!Repeater_2400_Edition International-de.docx | B4: 503 | D4: APa | E4: DE | H4: Mail | I4: 45701 | J4: 46069 | K4: 46073 | L4: =IF(_xlfn.XLOOKUP(D4, ABZ!A:A, ABZ!B:B, "", 0) = 0, "", _xlfn.XLOOKUP(D4, ABZ!A:A, ABZ!B:B, "", 0)) -> Sales Marketing | M4: Ü-fertig | N4: Hme | O4: Z:\Produkte\Texte Web, Marketing, etc\deutsch\2026.02 | P4: Entwicklung
A5: 2026_Ankuendigung_FRITZ!Repeater_2400_Edition International-de.docx | B5: 503 | D5: APa | E5: PL | F5: Yabylon | H5: Mail | I5: 45701 | J5: 46069 | K5: 46073 | L5: =IF(_xlfn.XLOOKUP(D5, ABZ!A:A, ABZ!B:B, "", 0) = 0, "", _xlfn.XLOOKUP(D5, ABZ!A:A, ABZ!B:B, "", 0)) -> Sales Marketing | M5: geliefert | N5: Hme | O5: Z:\Produkte\Texte Web, Marketing, etc\deutsch\2026.02 | P5: Entwicklung
A6: 2026_Ankuendigung_FRITZ!Repeater 600 Edition International-de.docx | B6: 443 | D6: APa | E6: DE | H6: Mail | I6: 45701 | J6: 46069 | K6: 46073 | L6: =IF(_xlfn.XLOOKUP(D6, ABZ!A:A, ABZ!B:B, "", 0) = 0, "", _xlfn.XLOOKUP(D6, ABZ!A:A, ABZ!B:B, "", 0)) -> Sales Marketing | M6: Ü-fertig | N6: Hme | O6: Z:\Produkte\Texte Web, Marketing, etc\deutsch\2026.02 | P6: Entwicklung
A7: 2026_Ankuendigung_FRITZ!Repeater 600 Edition International-de.docx | B7: 443 | D7: APa | E7: Pl | F7: Yabylon | H7: Mail | I7: 45701 | J7: 46069 | K7: 46073 | L7: =IF(_xlfn.XLOOKUP(D7, ABZ!A:A, ABZ!B:B, "", 0) = 0, "", _xlfn.XLOOKUP(D7, ABZ!A:A, ABZ!B:B, "", 0)) -> Sales Marketing | M7: geliefert | N7: Hme | O7: Z:\Produkte\Texte Web, Marketing, etc\deutsch\2026.02 | P7: Entwicklung
A8: NL_Newsletter_März.docx | B8: 514 | D8: Pse | E8: NL | F8: Angelique | H8: LS-Tracker | I8: 45720 | J8: 46091 | K8: 46094 | L8: =IF(_xlfn.XLOOKUP(D8, ABZ!A:A, ABZ!B:B, "", 0) = 0, "", _xlfn.XLOOKUP(D8, ABZ!A:A, ABZ!B:B, "", 0)) -> Channel Sales | M8: geliefert | N8: Hme | O8: BP-Technik | P8: Entwicklung
A9: 4614_en-GB_technik_20260304-092633.xml | B9: 367 | D9: Pse | E9: EN | F9: John | H9: LS-Tracker | I9: 45720 | J9: 46101 | K9: 46101 | L9: =IF(_xlfn.XLOOKUP(D9, ABZ!A:A, ABZ!B:B, "", 0) = 0, "", _xlfn.XLOOKUP(D9, ABZ!A:A, ABZ!B:B, "", 0)) -> Channel Sales | M9: geliefert | N9: Hme | O9: BP-Technik | P9: Vertrieb
A10: 4746_en-GB_security_und_software_20260304-091506.xml | B10: 104 | D10: Pse | E10: EN | F10: John | H10: LS-Tracker | I10: 45720 | J10: 46101 | K10: 46101 | L10: =IF(_xlfn.XLOOKUP(D10, ABZ!A:A, ABZ!B:B, "", 0) = 0, "", _xlfn.XLOOKUP(D10, ABZ!A:A, ABZ!B:B, "", 0)) -> Channel Sales | M10: geliefert | N10: Hme | O10: BP-Technik | P10: Vertrieb
A11: 4747_en-GB_failsafe_20260304-091557.xml | B11: 295 | D11: Pse | E11: EN | F11: John | H11: LS-Tracker | I11: 45720 | J11: 46101 | K11: 46101 | L11: =IF(_xlfn.XLOOKUP(D11, ABZ!A:A, ABZ!B:B, "", 0) = 0, "", _xlfn.XLOOKUP(D11, ABZ!A:A, ABZ!B:B, "", 0)) -> Channel Sales | M11: geliefert | N11: Hme | O11: BP-Technik | P11: D2C
A12: 4748_en-GB_fritz_wissensdatenbank_20260304-091553.xml | B12: 277 | D12: Pse | E12: EN | F12: John | H12: LS-Tracker | I12: 45720 | J12: 46101 | K12: 46101 | L12: =IF(_xlfn.XLOOKUP(D12, ABZ!A:A, ABZ!B:B, "", 0) = 0, "", _xlfn.XLOOKUP(D12, ABZ!A:A, ABZ!B:B, "", 0)) -> Channel Sales | M12: geliefert | N12: Hme | O12: BP-Technik | P12: D2C
A13: 4749_en-GB_upload_freigabe_fuer_einfachen_dateiaustausch_20260304-091549.xml | B13: 409 | D13: Pse | E13: EN | F13: John | H13: LS-Tracker | I13: 45720 | J13: 46101 | K13: 46101 | L13: =IF(_xlfn.XLOOKUP(D13, ABZ!A:A, ABZ!B:B, "", 0) = 0, "", _xlfn.XLOOKUP(D13, ABZ!A:A, ABZ!B:B, "", 0)) -> Channel Sales | M13: geliefert | N13: Hme | O13: BP-Technik | P13: D2C
A14: 4750_en-GB_wi_fi_7_das_multi_gigabit_wlan_ist_da_20260304-091544.xml | B14: 526 | D14: Pse | E14: EN | F14: Lisa | H14: LS-Tracker | I14: 45720 | J14: 46101 | K14: 46101 | L14: =IF(_xlfn.XLOOKUP(D14, ABZ!A:A, ABZ!B:B, "", 0) = 0, "", _xlfn.XLOOKUP(D14, ABZ!A:A, ABZ!B:B, "", 0)) -> Channel Sales | M14: geliefert | N14: Hme | O14: BP-Technik | P14: D2C
A15: 4751_en-GB_smart_home_mit_fritz_und_matter_20260304-091540.xml | B15: 463 | D15: Pse | E15: EN | F15: Lisa | H15: LS-Tracker | I15: 45720 | J15: 46101 | K15: 46101 | L15: =IF(_xlfn.XLOOKUP(D15, ABZ!A:A, ABZ!B:B, "", 0) = 0, "", _xlfn.XLOOKUP(D15, ABZ!A:A, ABZ!B:B, "", 0)) -> Channel Sales | M15: geliefert | N15: Hme | O15: BP-Technik | P15: D2C
A16: 4752_en-GB_smart_home_mit_fritz_und_zigbee_20260304-091535.xml | B16: 1083 | D16: Pse | E16: EN | F16: Lisa | H16: LS-Tracker | I16: 45720 | J16: 46101 | K16: 46101 | L16: =IF(_xlfn.XLOOKUP(D16, ABZ!A:A, ABZ!B:B, "", 0) = 0, "", _xlfn.XLOOKUP(D16, ABZ!A:A, ABZ!B:B, "", 0)) -> Channel Sales | M16: geliefert | N16: Hme | O16: BP-Technik | P16: KM
A17: 4753_en-GB_schon_gewusst_20260304-091608.xml | B17: 166 | D17: Pse | E17: EN | F17: Lisa | H17: LS-Tracker | I17: 45720 | J17: 46101 | K17: 46101 | L17: =IF(_xlfn.XLOOKUP(D17, ABZ!A:A, ABZ!B:B, "", 0) = 0, "", _xlfn.XLOOKUP(D17, ABZ!A:A, ABZ!B:B, "", 0)) -> Channel Sales | M17: geliefert | N17: Hme | O17: BP-Technik | P17: KM
A18: 4754_en-GB_internetnutzung_im_unternehmen_gezielt_steuern_20260304-091522.xml | B18: 668 | D18: Pse | E18: EN | F18: Susan | H18: LS-Tracker | I18: 45720 | J18: 46101 | K18: 46101 | L18: =IF(_xlfn.XLOOKUP(D18, ABZ!A:A, ABZ!B:B, "", 0) = 0, "", _xlfn.XLOOKUP(D18, ABZ!A:A, ABZ!B:B, "", 0)) -> Channel Sales | M18: geliefert | N18: Hme | O18: BP-Technik | P18: KM
... A27: Übersetzung Stichpunkte für Social Media Karussell | B27: 53 | D27: KGo | E27: FR | F27: Marie | H27: Mail | I27: 46021 | J27: 46038 | K27: 46038 | L27: =IF(_xlfn.XLOOKUP(D27, ABZ!A:A, ABZ!B:B, "", 0) = 0, "", _xlfn.XLOOKUP(D27, ABZ!A:A, ABZ!B:B, "", 0)) -> D2C Ecommerce | M27: geliefert | N27: Hme | O27: Z:\Produkte\Texte Web, Marketing, etc\deutsch\2025.12 | P27: D2C
A28: 2026-01-06T14-01-35_PM-History-Texts.xml | D28: TJa | E28: DE | H28: Mail | I28: 46027 | J28: 46027 | K28: 46027 | L28: =IF(_xlfn.XLOOKUP(D28, ABZ!A:A, ABZ!B:B, "", 0) = 0, "", _xlfn.XLOOKUP(D28, ABZ!A:A, ABZ!B:B, "", 0)) -> Product Management | M28: geliefert | N28: FSc | O28: Z:\Produkte\F!Box allgemein\Info.txt\Release\25_Smart24-P2\2026.01 | P28: D2C
A29: 2026-01-06T14-40-23_PM-History-Texts_korr-de.xml | D29: TJa | E29: EN | F29: John | H29: Mail | I29: 46027 | J29: 46027 | K29: 46027 | L29: =IF(_xlfn.XLOOKUP(D29, ABZ!A:A, ABZ!B:B, "", 0) = 0, "", _xlfn.XLOOKUP(D29, ABZ!A:A, ABZ!B:B, "", 0)) -> Product Management | M29: geliefert | N29: FSc | O29: Z:\Produkte\F!Box allgemein\Info.txt\Release\25_Smart24-P2\2026.01 | P29: D2C
A30: IT-Standalone-NL-2026.docx | B30: 255 | D30: Jwg | E30: IT | F30: Cristina | G30: Laura | H30: Mail | I30: 46027 | J30: 46034 | K30: 46034 | L30: =IF(_xlfn.XLOOKUP(D30, ABZ!A:A, ABZ!B:B, "", 0) = 0, "", _xlfn.XLOOKUP(D30, ABZ!A:A, ABZ!B:B, "", 0)) -> Channel Sales | M30: geliefert | N30: Msi | O30: Z:\Produkte\FRITZ!com\deutsch\2026.01 | P30: D2C
A31: Übersetzung Januar newsletter NL.docx | B31: 269 | D31: Pse | E31: NL | F31: Angelique | H31: Mail | I31: 46027 | J31: 46031 | K31: 46035 | L31: =IF(_xlfn.XLOOKUP(D31, ABZ!A:A, ABZ!B:B, "", 0) = 0, "", _xlfn.XLOOKUP(D31, ABZ!A:A, ABZ!B:B, "", 0)) -> Channel Sales | N31: Msi | O31: Z:\Produkte\FRITZ!com\deutsch\2026.01 | P31: D2C
A32: v7 | B32: 519 | D32: Dhr | E32: EN | F32: John | H32: Mail | I32: 46027 | J32: 46028 | K32: 46028 | L32: =IF(_xlfn.XLOOKUP(D32, ABZ!A:A, ABZ!B:B, "", 0) = 0, "", _xlfn.XLOOKUP(D32, ABZ!A:A, ABZ!B:B, "", 0)) -> Corporate Communications | N32: Msi | O32: Z:\Produkte\FRITZ!com\deutsch\2026.01 | P32: Vertrieb
A33: Information zu Speicherkrise 18122025.docx | B33: 519 | D33: Dhr | E33: IT | F33: Cristina | G33: Laura | H33: Mail | I33: 46027 | J33: 46029 | K33: 46028 | L33: =IF(_xlfn.XLOOKUP(D33, ABZ!A:A, ABZ!B:B, "", 0) = 0, "", _xlfn.XLOOKUP(D33, ABZ!A:A, ABZ!B:B, "", 0)) -> Corporate Communications | N33: Msi | O33: Z:\Produkte\FRITZ!com\deutsch\2026.01 | P33: Entwicklung
A34: Information zu Speicherkrise 18122025.docx | B34: 519 | D34: Dhr | E34: NL | F34: Marion | G34: Angelique | H34: Mail | I34: 46027 | J34: 46029 | K34: 46028 | L34: =IF(_xlfn.XLOOKUP(D34, ABZ!A:A, ABZ!B:B, "", 0) = 0, "", _xlfn.XLOOKUP(D34, ABZ!A:A, ABZ!B:B, "", 0)) -> Corporate Communications | N34: Msi | O34: Z:\Produkte\FRITZ!com\deutsch\2026.01 | P34: Entwicklung
A35: METAFIELDS | D35: CST | E35: EN | F35: John | H35: Mail | I35: 46028 | J35: 46030 | K35: 46034 | L35: =IF(_xlfn.XLOOKUP(D35, ABZ!A:A, ABZ!B:B, "", 0) = 0, "", _xlfn.XLOOKUP(D35, ABZ!A:A, ABZ!B:B, "", 0)) -> D2C Ecommerce | N35: Lbo | O35: Z:\Produkte\FRITZ!com\deutsch\2026.01\KW2 | P35: Entwicklung
A36: METAFIELDS | D36: CST | E36: ES | F36: Helena | H36: Mail | I36: 46028 | J36: 46029 | K36: 46034 | L36: =IF(_xlfn.XLOOKUP(D36, ABZ!A:A, ABZ!B:B, "", 0) = 0, "", _xlfn.XLOOKUP(D36, ABZ!A:A, ABZ!B:B, "", 0)) -> D2C Ecommerce | M36: geliefert | N36: Lbo | O36: Z:\Produkte\FRITZ!com\deutsch\2026.01\KW2 | P36: Entwicklung
A37: METAFIELDS | D37: CST | E37: FR | F37: Martine | H37: Mail | I37: 46028 | J37: 46030 | K37: 46034 | L37: =IF(_xlfn.XLOOKUP(D37, ABZ!A:A, ABZ!B:B, "", 0) = 0, "", _xlfn.XLOOKUP(D37, ABZ!A:A, ABZ!B:B, "", 0)) -> D2C Ecommerce | M37: ausgecheckt | N37: Lbo | O37: Z:\Produkte\FRITZ!com\deutsch\2026.01\KW2 | P37: Entwicklung
A38: METAFIELDS | D38: CST | E38: IT | F38: Laura | H38: Mail | I38: 46028 | J38: 46030 | K38: 46034 | L38: =IF(_xlfn.XLOOKUP(D38, ABZ!A:A, ABZ!B:B, "", 0) = 0, "", _xlfn.XLOOKUP(D38, ABZ!A:A, ABZ!B:B, "", 0)) -> D2C Ecommerce | N38: Lbo | O38: Z:\Produkte\FRITZ!com\deutsch\2026.01\KW2 | P38: Entwicklung
A39: METAFIELDS | D39: CST | E39: NL | F39: Angelique | H39: Mail | I39: 46028 | J39: 46030 | K39: 46034 | L39: =IF(_xlfn.XLOOKUP(D39, ABZ!A:A, ABZ!B:B, "", 0) = 0, "", _xlfn.XLOOKUP(D39, ABZ!A:A, ABZ!B:B, "", 0)) -> D2C Ecommerce | M39: NICHT ausgecheckt | N39: Lbo | O39: Z:\Produkte\FRITZ!com\deutsch\2026.01\KW2 | P39: Entwicklung
A40: Newsletter-IT-01-26.docx | B40: 44 | D40: Jwg | E40: IT | F40: Cristina | G40: Laura | H40: Mail | I40: 46028 | J40: 46038 | K40: 46037 | L40: =IF(_xlfn.XLOOKUP(D40, ABZ!A:A, ABZ!B:B, "", 0) = 0, "", _xlfn.XLOOKUP(D40, ABZ!A:A, ABZ!B:B, "", 0)) -> Channel Sales | M40: geliefert | N40: Hme | O40: Z:\Produkte\FRITZ!com\deutsch\2026.01 | P40: Entwicklung
A41: Newsletter-ES-01-26.docx | B41: 128 | D41: Jwg | E41: ES | F41: Alba | H41: Mail | I41: 46028 | J41: 46038 | K41: 46037 | L41: =IF(_xlfn.XLOOKUP(D41, ABZ!A:A, ABZ!B:B, "", 0) = 0, "", _xlfn.XLOOKUP(D41, ABZ!A:A, ABZ!B:B, "", 0)) -> Channel Sales | M41: geliefert | N41: Hme | O41: Z:\Produkte\FRITZ!com\deutsch\2026.01 | P41: Kommunikation
A42: MyFapp_20260107-de.xml | D42: KSu | E42: DE | F42: Carsten | G42: Franziska | H42: jazz | I42: 46029 | J42: 46030 | K42: 46030 | L42: =IF(_xlfn.XLOOKUP(D42, ABZ!A:A, ABZ!B:B, "", 0) = 0, "", _xlfn.XLOOKUP(D42, ABZ!A:A, ABZ!B:B, "", 0)) -> User Interface & Clients | M42: geliefert | N42: FSc | O42: Z:\Produkte\F!Apps\FappMyF\GUI\Android\deutsch\2026.01 | P42: Vertrieb
A43: Übersetzung Newsletter Solden-de.docx | B43: 36 | D43: Atc | E43: Nl | F43: Angelique | H43: Mail | I43: 46029 | J43: 46034 | K43: 46031 | L43: =IF(_xlfn.XLOOKUP(D43, ABZ!A:A, ABZ!B:B, "", 0) = 0, "", _xlfn.XLOOKUP(D43, ABZ!A:A, ABZ!B:B, "", 0)) -> D2C Ecommerce | M43: geliefert | N43: Hme | O43: Z:\Produkte\FRITZ!com\deutsch\2026.01 | P43: D2C
A44: MyFapp_20260107-de.xml | D44: KSu | E44: EN | F44: John | H44: jazz | I44: 46029 | J44: 46034 | K44: 46034 | L44: =IF(_xlfn.XLOOKUP(D44, ABZ!A:A, ABZ!B:B, "", 0) = 0, "", _xlfn.XLOOKUP(D44, ABZ!A:A, ABZ!B:B, "", 0)) -> User Interface & Clients | M44: geliefert | N44: FSc | O44: Z:\Produkte\F!Apps\FappMyF\GUI\Android\deutsch\2026.01 | P44: D2C
A45: MyFapp_20260107-de.xml | D45: KSu | E45: Es | F45: Helena | H45: jazz | I45: 46029 | J45: 46034 | K45: 46034 | L45: =IF(_xlfn.XLOOKUP(D45, ABZ!A:A, ABZ!B:B, "", 0) = 0, "", _xlfn.XLOOKUP(D45, ABZ!A:A, ABZ!B:B, "", 0)) -> User Interface & Clients | M45: geliefert | N45: FSc | O45: Z:\Produkte\F!Apps\FappMyF\GUI\Android\deutsch\2026.01 | P45: D2C
A46: MyFapp_20260107-de.xml | D46: KSu | E46: Fr | F46: Marie | H46: jazz | I46: 46029 | J46: 46034 | K46: 46034 | L46: =IF(_xlfn.XLOOKUP(D46, ABZ!A:A, ABZ!B:B, "", 0) = 0, "", _xlfn.XLOOKUP(D46, ABZ!A:A, ABZ!B:B, "", 0)) -> User Interface & Clients | M46: geliefert | N46: FSc | O46: Z:\Produkte\F!Apps\FappMyF\GUI\Android\deutsch\2026.01 | P46: D2C
A47: MyFapp_20260107-de.xml | D47: KSu | E47: It | F47: Laura | H47: jazz | I47: 46029 | J47: 46034 | K47: 46034 | L47: =IF(_xlfn.XLOOKUP(D47, ABZ!A:A, ABZ!B:B, "", 0) = 0, "", _xlfn.XLOOKUP(D47, ABZ!A:A, ABZ!B:B, "", 0)) -> User Interface & Clients | M47: geliefert | N47: FSc | O47: Z:\Produkte\F!Apps\FappMyF\GUI\Android\deutsch\2026.01 | P47: D2C
A48: MyFapp_20260107-de.xml | D48: KSu | E48: Nl | F48: Angelique | H48: jazz | I48: 46029 | J48: 46034 | K48: 46034 | L48: =IF(_xlfn.XLOOKUP(D48, ABZ!A:A, ABZ!B:B, "", 0) = 0, "", _xlfn.XLOOKUP(D48, ABZ!A:A, ABZ!B:B, "", 0)) -> User Interface & Clients | M48: geliefert | N48: FSc | O48: Z:\Produkte\F!Apps\FappMyF\GUI\Android\deutsch\2026.01 | P48: KM
A49: MyFapp_20260107-de.xml | D49: KSu | E49: Pl | F49: Yabylon | H49: jazz | I49: 46029 | J49: 46034 | K49: 46034 | L49: =IF(_xlfn.XLOOKUP(D49, ABZ!A:A, ABZ!B:B, "", 0) = 0, "", _xlfn.XLOOKUP(D49, ABZ!A:A, ABZ!B:B, "", 0)) -> User Interface & Clients | M49: geliefert | N49: FSc | O49: Z:\Produkte\F!Apps\FappMyF\GUI\Android\deutsch\2026.01 | P49: KM
A50: MyFapp_20260107-de.xml | D50: KSu | E50: SL | F50: Yabylon | H50: jazz | I50: 46029 | J50: 46034 | K50: 46034 | L50: =IF(_xlfn.XLOOKUP(D50, ABZ!A:A, ABZ!B:B, "", 0) = 0, "", _xlfn.XLOOKUP(D50, ABZ!A:A, ABZ!B:B, "", 0)) -> User Interface & Clients | M50: geliefert | N50: FSc | O50: Z:\Produkte\F!Apps\FappMyF\GUI\Android\deutsch\2026.01 | P50: KM
A51: Übersetzung Abbinder Newsletter D2C_de.docx | B51: 16 | D51: Atc | E51: EN | F51: John | H51: Mail | I51: 46029 | J51: 46036 | K51: 46036 | L51: =IF(_xlfn.XLOOKUP(D51, ABZ!A:A, ABZ!B:B, "", 0) = 0, "", _xlfn.XLOOKUP(D51, ABZ!A:A, ABZ!B:B, "", 0)) -> D2C Ecommerce | M51: geliefert | N51: Hme | O51: Z:\Produkte\FRITZ!com\deutsch\2026.01 | P51: KM
A52: Übersetzung Abbinder Newsletter D2C_de.docx | B52: 16 | D52: Atc | E52: NL | F52: Angelique | H52: Mail | I52: 46029 | J52: 46036 | K52: 46036 | L52: =IF(_xlfn.XLOOKUP(D52, ABZ!A:A, ABZ!B:B, "", 0) = 0, "", _xlfn.XLOOKUP(D52, ABZ!A:A, ABZ!B:B, "", 0)) -> D2C Ecommerce | M52: geliefert | N52: Hme | O52: Z:\Produkte\FRITZ!com\deutsch\2026.01 | P52: KM
A53: Übersetzung Abbinder Newsletter D2C_de.docx | B53: 16 | D53: Atc | E53: IT | F53: Laura | H53: Mail | I53: 46029 | J53: 46036 | K53: 46036 | L53: =IF(_xlfn.XLOOKUP(D53, ABZ!A:A, ABZ!B:B, "", 0) = 0, "", _xlfn.XLOOKUP(D53, ABZ!A:A, ABZ!B:B, "", 0)) -> D2C Ecommerce | M53: ausgecheckt | N53: Hme | O53: Z:\Produkte\FRITZ!com\deutsch\2026.01 | P53: KM
A54: Übersetzung Abbinder Newsletter D2C_de.docx | B54: 16 | D54: Atc | E54: ES | F54: Alba | H54: Mail | I54: 46029 | J54: 46036 | K54: 46036 | L54: =IF(_xlfn.XLOOKUP(D54, ABZ!A:A, ABZ!B:B, "", 0) = 0, "", _xlfn.XLOOKUP(D54, ABZ!A:A, ABZ!B:B, "", 0)) -> D2C Ecommerce | M54: geliefert | N54: Hme | O54: Z:\Produkte\FRITZ!com\deutsch\2026.01 | P54: KM
A55: Data Act FRITZ!Smart-int-de.docx | B55: 341 | D55: LLe | E55: It | F55: Cristina | G55: Laura | H55: Mail | I55: 46029 | J55: 46043 | K55: 46045 | L55: =IF(_xlfn.XLOOKUP(D55, ABZ!A:A, ABZ!B:B, "", 0) = 0, "", _xlfn.XLOOKUP(D55, ABZ!A:A, ABZ!B:B, "", 0)) -> Technical Communication | M55: geliefert | N55: FSc | O55: Z:\Produkte\Einleger und juristische Texte\Data Act\FRITZ!Smart\2026.01 | P55: KM
A56: Data Act FRITZ!Smart-int-de.docx | B56: 341 | D56: LLe | E56: Nl | F56: Angelique | H56: Mail | I56: 46029 | J56: 46038 | K56: 46045 | L56: =IF(_xlfn.XLOOKUP(D56, ABZ!A:A, ABZ!B:B, "", 0) = 0, "", _xlfn.XLOOKUP(D56, ABZ!A:A, ABZ!B:B, "", 0)) -> Technical Communication | M56: geliefert | N56: FSc | O56: Z:\Produkte\Einleger und juristische Texte\Data Act\FRITZ!Smart\2026.01 | P56: KM
A57: Data Act FRITZ!Smart-int-de.docx | B57: 341 | D57: LLe | E57: DA | F57: Yabylon | H57: Mail | I57: 46029 | J57: 46036 | K57: 46052 | L57: =IF(_xlfn.XLOOKUP(D57, ABZ!A:A, ABZ!B:B, "", 0) = 0, "", _xlfn.XLOOKUP(D57, ABZ!A:A, ABZ!B:B, "", 0)) -> Technical Communication | M57: geliefert | N57: FSc | O57: Z:\Produkte\Einleger und juristische Texte\Data Act\FRITZ!Smart\2026.01 | P57: KM
A58: Data Act FRITZ!Smart-int-de.docx | B58: 341 | D58: LLe | E58: EN | F58: John | H58: Mail | I58: 46029 | J58: 46036 | K58: 46052 | L58: =IF(_xlfn.XLOOKUP(D58, ABZ!A:A, ABZ!B:B, "", 0) = 0, "", _xlfn.XLOOKUP(D58, ABZ!A:A, ABZ!B:B, "", 0)) -> Technical Communication | M58: geliefert | N58: FSc | O58: Z:\Produkte\Einleger und juristische Texte\Data Act\FRITZ!Smart\2026.01 | P58: Vertrieb
A59: Data Act FRITZ!Smart-int-de.docx | B59: 341 | D59: LLe | E59: Es | F59: Alba | H59: Mail | I59: 46029 | J59: 46036 | K59: 46052 | L59: =IF(_xlfn.XLOOKUP(D59, ABZ!A:A, ABZ!B:B, "", 0) = 0, "", _xlfn.XLOOKUP(D59, ABZ!A:A, ABZ!B:B, "", 0)) -> Technical Communication | M59: geliefert | N59: FSc | O59: Z:\Produkte\Einleger und juristische Texte\Data Act\FRITZ!Smart\2026.01 | P59: Vertrieb
A60: Data Act FRITZ!Smart-int-de.docx | B60: 341 | D60: LLe | E60: Fi | F60: Yabylon | H60: Mail | I60: 46029 | J60: 46036 | K60: 46052 | L60: =IF(_xlfn.XLOOKUP(D60, ABZ!A:A, ABZ!B:B, "", 0) = 0, "", _xlfn.XLOOKUP(D60, ABZ!A:A, ABZ!B:B, "", 0)) -> Technical Communication | M60: geliefert | N60: FSc | O60: Z:\Produkte\Einleger und juristische Texte\Data Act\FRITZ!Smart\2026.01 | P60: Vertrieb
A61: Data Act FRITZ!Smart-int-de.docx | B61: 341 | D61: LLe | E61: Fr | F61: Marie | H61: Mail | I61: 46029 | J61: 46036 | K61: 46052 | L61: =IF(_xlfn.XLOOKUP(D61, ABZ!A:A, ABZ!B:B, "", 0) = 0, "", _xlfn.XLOOKUP(D61, ABZ!A:A, ABZ!B:B, "", 0)) -> Technical Communication | M61: geliefert | N61: FSc | O61: Z:\Produkte\Einleger und juristische Texte\Data Act\FRITZ!Smart\2026.01 | P61: Vertrieb
A62: Data Act FRITZ!Smart-int-de.docx | B62: 341 | D62: LLe | E62: NO | F62: Yabylon | H62: Mail | I62: 46029 | J62: 46036 | K62: 46052 | L62: =IF(_xlfn.XLOOKUP(D62, ABZ!A:A, ABZ!B:B, "", 0) = 0, "", _xlfn.XLOOKUP(D62, ABZ!A:A, ABZ!B:B, "", 0)) -> Technical Communication | M62: geliefert | N62: FSc | O62: Z:\Produkte\Einleger und juristische Texte\Data Act\FRITZ!Smart\2026.01 | P62: Vertrieb
A63: Data Act FRITZ!Smart-int-de.docx | B63: 341 | D63: LLe | E63: Pl | F63: Yabylon | H63: Mail | I63: 46029 | J63: 46036 | K63: 46052 | L63: =IF(_xlfn.XLOOKUP(D63, ABZ!A:A, ABZ!B:B, "", 0) = 0, "", _xlfn.XLOOKUP(D63, ABZ!A:A, ABZ!B:B, "", 0)) -> Technical Communication | M63: geliefert | N63: FSc | O63: Z:\Produkte\Einleger und juristische Texte\Data Act\FRITZ!Smart\2026.01 | P63: Vertrieb
A64: Data Act FRITZ!Smart-int-de.docx | B64: 341 | D64: LLe | E64: SV | F64: Yabylon | H64: Mail | I64: 46029 | J64: 46036 | K64: 46052 | L64: =IF(_xlfn.XLOOKUP(D64, ABZ!A:A, ABZ!B:B, "", 0) = 0, "", _xlfn.XLOOKUP(D64, ABZ!A:A, ABZ!B:B, "", 0)) -> Technical Communication | M64: geliefert | N64: FSc | O64: Z:\Produkte\Einleger und juristische Texte\Data Act\FRITZ!Smart\2026.01 | P64: Vertrieb
A65: Data Act FRITZ!Smart-int-de.docx | B65: 341 | D65: LLe | E65: SL | F65: Yabylon | H65: Mail | I65: 46029 | J65: 46036 | K65: 46052 | L65: =IF(_xlfn.XLOOKUP(D65, ABZ!A:A, ABZ!B:B, "", 0) = 0, "", _xlfn.XLOOKUP(D65, ABZ!A:A, ABZ!B:B, "", 0)) -> Technical Communication | M65: geliefert | N65: FSc | O65: Z:\Produkte\Einleger und juristische Texte\Data Act\FRITZ!Smart\2026.01 | P65: Vertrieb
A66: Frohes neues Jahr 2026.docx | B66: 83 | D66: Pse | E66: NL | F66: Angelique | H66: Mail | I66: 46030 | J66: 46030 | K66: 46030 | L66: =IF(_xlfn.XLOOKUP(D66, ABZ!A:A, ABZ!B:B, "", 0) = 0, "", _xlfn.XLOOKUP(D66, ABZ!A:A, ABZ!B:B, "", 0)) -> Channel Sales | N66: Msi | O66: Z:\Produkte\FRITZ!com\deutsch\2026.01 | P66: Vertrieb
A67: MWC-save-the-date-2026-de.docx | B67: 112 | D67: BAl | E67: EN | F67: John | H67: Mail | I67: 46031 | J67: 46034 | K67: 46035 | L67: =IF(_xlfn.XLOOKUP(D67, ABZ!A:A, ABZ!B:B, "", 0) = 0, "", _xlfn.XLOOKUP(D67, ABZ!A:A, ABZ!B:B, "", 0)) -> Corporate Communications | M67: geliefert | N67: FSc | O67: Z:\Produkte\Texte Web, Marketing, etc\deutsch\2026.01 | P67: Vertrieb
A68: German_Design_Award-de.docx | B68: 101 | D68: PSe | E68: Nl | F68: Angelique | H68: Mail | I68: 46031 | J68: 46036 | K68: 46042 | L68: =IF(_xlfn.XLOOKUP(D68, ABZ!A:A, ABZ!B:B, "", 0) = 0, "", _xlfn.XLOOKUP(D68, ABZ!A:A, ABZ!B:B, "", 0)) -> Channel Sales | M68: geliefert | N68: FSc | O68: Z:\Produkte\Texte Web, Marketing, etc\deutsch\2026.01 | P68: Vertrieb
A69: OH_FB_s24p2_v7-2026-01-12_D-00000084_T-00000951_EngineeringModules_de-DE_en-GB.Fragments.xml | D69: Cmi | E69: EN | F69: John | H69: Mail | I69: 46034 | J69: 46041 | K69: 46041 | L69: =IF(_xlfn.XLOOKUP(D69, ABZ!A:A, ABZ!B:B, "", 0) = 0, "", _xlfn.XLOOKUP(D69, ABZ!A:A, ABZ!B:B, "", 0)) -> Technical Communication | M69: geliefert | N69: Msi | O69: Z:\International\Tico\work\2026-01-12_D-00000084_T-00000951_de-DE_en-GB.xml | P69: Vertrieb
A70: OH_FB_s24p2_v7-2026-01-12_D-00000084_T-00000951_EngineeringModules_de-DE_en-GB.xml | D70: Cmi | E70: EN | F70: John | H70: Mail | I70: 46034 | J70: 46041 | K70: 46041 | L70: =IF(_xlfn.XLOOKUP(D70, ABZ!A:A, ABZ!B:B, "", 0) = 0, "", _xlfn.XLOOKUP(D70, ABZ!A:A, ABZ!B:B, "", 0)) -> Technical Communication | M70: geliefert | N70: Msi | O70: Z:\International\Tico\work\2026-01-12_D-00000084_T-00000951_de-DE_en-GB.xml | P70: Vertrieb
A71: OH_FB_s24p2_v7-2026-01-12_D-00000084_T-00000948_EngineeringModules_de-DE_es-ES.xml | D71: Cmi | E71: Es | F71: Helena | H71: Mail | I71: 46034 | J71: 46038 | K71: 46041 | L71: =IF(_xlfn.XLOOKUP(D71, ABZ!A:A, ABZ!B:B, "", 0) = 0, "", _xlfn.XLOOKUP(D71, ABZ!A:A, ABZ!B:B, "", 0)) -> Technical Communication | M71: geliefert | N71: Msi | O71: Z:\International\Tico\work\2026-01-12_D-00000084_T-00000948_de-DE_es-ES.xml\untranslated | P71: D2C
A72: OH_FB_s24p2_v7-2026-01-12_D-00000084_T-00000947_EngineeringModules_de-DE_fr-FR.Fragments.xml | D72: Cmi | E72: Fr | F72: Martine | H72: Mail | I72: 46034 | J72: 46038 | K72: 46041 | L72: =IF(_xlfn.XLOOKUP(D72, ABZ!A:A, ABZ!B:B, "", 0) = 0, "", _xlfn.XLOOKUP(D72, ABZ!A:A, ABZ!B:B, "", 0)) -> Technical Communication | M72: geliefert | N72: Msi | O72: Z:\International\Tico\work\2026-01-12_D-00000084_T-00000947_de-DE_fr-FR.xml\untranslated | P72: D2C
A73: OH_FB_s24p2_v7-2026-01-12_D-00000084_T-00000949_EngineeringModules_de-DE_it-IT.Fragments.xml | D73: Cmi | E73: It | F73: Laura | H73: Mail | I73: 46034 | J73: 46042 | K73: 46045 | L73: =IF(_xlfn.XLOOKUP(D73, ABZ!A:A, ABZ!B:B, "", 0) = 0, "", _xlfn.XLOOKUP(D73, ABZ!A:A, ABZ!B:B, "", 0)) -> Technical Communication | M73: geliefert | N73: Msi | O73: Z:\International\Tico\work\2026-01-12_D-00000084_T-00000949_de-DE_it-IT.xml\untranslated | P73: D2C
A74: OH_FB_s24p2_v7-2026-01-12_D-00000084_T-00000949_EngineeringModules_de-DE_it-IT.xml | D74: Cmi | E74: It | F74: Laura | H74: Mail | I74: 46034 | J74: 46042 | K74: 46045 | L74: =IF(_xlfn.XLOOKUP(D74, ABZ!A:A, ABZ!B:B, "", 0) = 0, "", _xlfn.XLOOKUP(D74, ABZ!A:A, ABZ!B:B, "", 0)) -> Technical Communication | M74: geliefert | N74: Msi | O74: Z:\International\Tico\work\2026-01-12_D-00000084_T-00000949_de-DE_it-IT.xml\untranslated | P74: D2C
A75: OH_FB_s24p2_v7-2026-01-12_D-00000084_T-00000950_EngineeringModules_de-DE_nl-NL.Fragments.xml | D75: Cmi | E75: Nl | F75: Angelique | H75: Mail | I75: 46034 | J75: 46045 | K75: 46045 | L75: =IF(_xlfn.XLOOKUP(D75, ABZ!A:A, ABZ!B:B, "", 0) = 0, "", _xlfn.XLOOKUP(D75, ABZ!A:A, ABZ!B:B, "", 0)) -> Technical Communication | M75: geliefert | N75: Msi | O75: Z:\International\Tico\work\2026-01-12_D-00000084_T-00000950_de-DE_nl-NL.xml\untranslated | P75: D2C
A76: OH_FB_s24p2_v7-2026-01-12_D-00000084_T-00000950_EngineeringModules_de-DE_nl-NL.xml | D76: Cmi | E76: Nl | F76: Angelique | H76: Mail | I76: 46034 | J76: 46045 | K76: 46045 | L76: =IF(_xlfn.XLOOKUP(D76, ABZ!A:A, ABZ!B:B, "", 0) = 0, "", _xlfn.XLOOKUP(D76, ABZ!A:A, ABZ!B:B, "", 0)) -> Technical Communication | M76: geliefert | N76: Msi | O76: Z:\International\Tico\work\2026-01-12_D-00000084_T-00000950_de-DE_nl-NL.xml\untranslated | P76: D2C
A77: OH_FB_s24p2_v7-2026-01-12_D-00000084_T-00000948_EngineeringModules_de-DE_es-ES.Fragments.xml | D77: Cmi | E77: Es | F77: Helena | H77: Mail | I77: 46034 | J77: 46038 | K77: 46045 | L77: =IF(_xlfn.XLOOKUP(D77, ABZ!A:A, ABZ!B:B, "", 0) = 0, "", _xlfn.XLOOKUP(D77, ABZ!A:A, ABZ!B:B, "", 0)) -> Technical Communication | M77: geliefert | N77: Msi | O77: Z:\International\Tico\work\2026-01-12_D-00000084_T-00000948_de-DE_es-ES.xml\untranslated | P77: D2C
A78: OH_FB_s24p2_v7-2026-01-12_D-00000084_T-00000947_EngineeringModules_de-DE_fr-FR.xml | D78: Cmi | E78: Fr | F78: Martine | H78: Mail | I78: 46034 | J78: 46038 | K78: 46045 | L78: =IF(_xlfn.XLOOKUP(D78, ABZ!A:A, ABZ!B:B, "", 0) = 0, "", _xlfn.XLOOKUP(D78, ABZ!A:A, ABZ!B:B, "", 0)) -> Technical Communication | M78: geliefert | N78: Msi | O78: Z:\International\Tico\work\2026-01-12_D-00000084_T-00000947_de-DE_fr-FR.xml\untranslated | P78: D2C
A79: 20260113_Ankuendigung_FRITZ!Box 4630_Edition_International_DE_Final.docx | B79: 734 | D79: Apa | E79: DE | G79: Franziska | H79: Mail | I79: 46035 | J79: 46035 | K79: 46035 | L79: =IF(_xlfn.XLOOKUP(D79, ABZ!A:A, ABZ!B:B, "", 0) = 0, "", _xlfn.XLOOKUP(D79, ABZ!A:A, ABZ!B:B, "", 0)) -> Sales Marketing | M79: geliefert | N79: Hme | O79: Z:\Produkte\Texte Web, Marketing, etc\deutsch\2026.01 | P79: D2C
A80: Whitepaper-de.docx | B80: 26 | D80: PSe | E80: Es | F80: Alba | H80: Mail | I80: 46035 | J80: 46038 | K80: 46038 | L80: =IF(_xlfn.XLOOKUP(D80, ABZ!A:A, ABZ!B:B, "", 0) = 0, "", _xlfn.XLOOKUP(D80, ABZ!A:A, ABZ!B:B, "", 0)) -> Channel Sales | M80: geliefert | N80: FSc | O80: Z:\Produkte\Texte Web, Marketing, etc\deutsch\2026.01 | P80: D2C
A81: Whitepaper-de.docx | B81: 26 | D81: PSe | E81: It | F81: Cristina | H81: Mail | I81: 46035 | J81: 46038 | K81: 46038 | L81: =IF(_xlfn.XLOOKUP(D81, ABZ!A:A, ABZ!B:B, "", 0) = 0, "", _xlfn.XLOOKUP(D81, ABZ!A:A, ABZ!B:B, "", 0)) -> Channel Sales | M81: geliefert | N81: FSc | O81: Z:\Produkte\Texte Web, Marketing, etc\deutsch\2026.01 | P81: D2C
A82: Whitepaper-de.docx | B82: 26 | D82: PSe | E82: Nl | F82: Angelique | H82: Mail | I82: 46035 | J82: 46038 | K82: 46038 | L82: =IF(_xlfn.XLOOKUP(D82, ABZ!A:A, ABZ!B:B, "", 0) = 0, "", _xlfn.XLOOKUP(D82, ABZ!A:A, ABZ!B:B, "", 0)) -> Channel Sales | M82: geliefert | N82: FSc | O82: Z:\Produkte\Texte Web, Marketing, etc\deutsch\2026.01 | P82: D2C
A83: 20260113_Ankuendigung_FRITZ!Box 4630_Edition_International_DE_Final.docx | B83: 734 | D83: Apa | E83: EN | F83: Susan | H83: Mail | I83: 46035 | J83: 46043 | K83: 46043 | L83: =IF(_xlfn.XLOOKUP(D83, ABZ!A:A, ABZ!B:B, "", 0) = 0, "", _xlfn.XLOOKUP(D83, ABZ!A:A, ABZ!B:B, "", 0)) -> Sales Marketing | M83: geliefert | N83: Hme | O83: Z:\Produkte\Texte Web, Marketing, etc\deutsch\2026.01 | P83: D2C
A84: 20260113_Ankuendigung_FRITZ!Box 4630_Edition_International_DE_Final.docx | B84: 734 | D84: Apa | E84: FR | F84: Marie | H84: Mail | I84: 46035 | J84: 46043 | K84: 46043 | L84: =IF(_xlfn.XLOOKUP(D84, ABZ!A:A, ABZ!B:B, "", 0) = 0, "", _xlfn.XLOOKUP(D84, ABZ!A:A, ABZ!B:B, "", 0)) -> Sales Marketing | M84: geliefert | N84: Hme | O84: Z:\Produkte\Texte Web, Marketing, etc\deutsch\2026.01 | P84: Entwicklung
A85: 20260113_Ankuendigung_FRITZ!Box 4630_Edition_International_DE_Final.docx | B85: 734 | D85: Apa | E85: NL | F85: Angelique | H85: Mail | I85: 46035 | J85: 46043 | K85: 46043 | L85: =IF(_xlfn.XLOOKUP(D85, ABZ!A:A, ABZ!B:B, "", 0) = 0, "", _xlfn.XLOOKUP(D85, ABZ!A:A, ABZ!B:B, "", 0)) -> Sales Marketing | M85: geliefert | N85: Hme | O85: Z:\Produkte\Texte Web, Marketing, etc\deutsch\2026.01 | P85: Vertrieb
A86: 20260113_Ankuendigung_FRITZ!Box 4630_Edition_International_DE_Final.docx | B86: 734 | D86: Apa | E86: ES | F86: Alba | H86: Mail | I86: 46035 | J86: 46043 | K86: 46043 | L86: =IF(_xlfn.XLOOKUP(D86, ABZ!A:A, ABZ!B:B, "", 0) = 0, "", _xlfn.XLOOKUP(D86, ABZ!A:A, ABZ!B:B, "", 0)) -> Sales Marketing | M86: geliefert | N86: Hme | O86: Z:\Produkte\Texte Web, Marketing, etc\deutsch\2026.01 | P86: Entwicklung
A87: 20260113_Ankuendigung_FRITZ!Box 4630_Edition_International_DE_Final.docx | B87: 734 | D87: Apa | E87: IT | F87: Cristina | G87: Laura | H87: Mail | I87: 46035 | J87: 46043 | K87: 46043 | L87: =IF(_xlfn.XLOOKUP(D87, ABZ!A:A, ABZ!B:B, "", 0) = 0, "", _xlfn.XLOOKUP(D87, ABZ!A:A, ABZ!B:B, "", 0)) -> Sales Marketing | M87: geliefert | N87: Hme | O87: Z:\Produkte\Texte Web, Marketing, etc\deutsch\2026.01 | P87: Entwicklung
A88: 20260114_MyFRITZ 3.0 Beschreibungstext AppStores_DE.docx | B88: 313 | D88: OKE | E88: EN | F88: Susan | H88: Mail | I88: 46036 | J88: 46041 | K88: 46042 | L88: =IF(_xlfn.XLOOKUP(D88, ABZ!A:A, ABZ!B:B, "", 0) = 0, "", _xlfn.XLOOKUP(D88, ABZ!A:A, ABZ!B:B, "", 0)) -> Channel Sales | M88: geliefert | N88: Hme | O88: Z:\Produkte\Texte Web, Marketing, etc\deutsch\2026.01 | P88: Entwicklung
A89: 20260114_MyFRITZ 3.0 Beschreibungstext AppStores_DE.docx | B89: 313 | D89: OKE | E89: FR | F89: Marie | H89: Mail | I89: 46036 | J89: 46041 | K89: 46042 | L89: =IF(_xlfn.XLOOKUP(D89, ABZ!A:A, ABZ!B:B, "", 0) = 0, "", _xlfn.XLOOKUP(D89, ABZ!A:A, ABZ!B:B, "", 0)) -> Channel Sales | M89: geliefert | N89: Hme | O89: Z:\Produkte\Texte Web, Marketing, etc\deutsch\2026.01 | P89: Entwicklung
A90: 20260114_MyFRITZ 3.0 Beschreibungstext AppStores_DE.docx | B90: 313 | D90: OKE | E90: IT | F90: Cristina | G90: Laura | H90: Mail | I90: 46036 | J90: 46041 | K90: 46042 | L90: =IF(_xlfn.XLOOKUP(D90, ABZ!A:A, ABZ!B:B, "", 0) = 0, "", _xlfn.XLOOKUP(D90, ABZ!A:A, ABZ!B:B, "", 0)) -> Channel Sales | M90: geliefert | N90: Hme | O90: Z:\Produkte\Texte Web, Marketing, etc\italienisch\2026.01 | P90: Entwicklung
A91: 20260114_MyFRITZ 3.0 Beschreibungstext AppStores_DE.docx | B91: 313 | D91: OKE | E91: NL | F91: Angelique | H91: Mail | I91: 46036 | J91: 46041 | K91: 46042 | L91: =IF(_xlfn.XLOOKUP(D91, ABZ!A:A, ABZ!B:B, "", 0) = 0, "", _xlfn.XLOOKUP(D91, ABZ!A:A, ABZ!B:B, "", 0)) -> Channel Sales | M91: geliefert | N91: Hme | O91: Z:\Produkte\Texte Web, Marketing, etc\deutsch\2026.01 | P91: Entwicklung
A92: Launch-Kampagne CH - Textassets_ Fritz_REG140126.xlsx | D92: REG | E92: DE | G92: Franziska | H92: Mail | I92: 46036 | J92: 46045 | K92: 46045 | L92: =IF(_xlfn.XLOOKUP(D92, ABZ!A:A, ABZ!B:B, "", 0) = 0, "", _xlfn.XLOOKUP(D92, ABZ!A:A, ABZ!B:B, "", 0)) -> D2C Ecommerce | M92: geliefert | N92: Hme | O92: Z:\Produkte\Texte Web, Marketing, etc\deutsch\2026.01 | P92: Entwicklung
A93: Launch-Kampagne CH - Textassets_ Fritz_REG140126.xlsx | D93: REG | E93: IT | F93: Laura | H93: Mail | I93: 46036 | J93: 46045 | K93: 46045 | L93: =IF(_xlfn.XLOOKUP(D93, ABZ!A:A, ABZ!B:B, "", 0) = 0, "", _xlfn.XLOOKUP(D93, ABZ!A:A, ABZ!B:B, "", 0)) -> D2C Ecommerce | M93: geliefert | N93: Hme | O93: Z:\Produkte\Texte Web, Marketing, etc\deutsch\2026.01 | P93: Vertrieb
A94: Launch-Kampagne CH - Textassets_ Fritz_REG140126.xlsx | D94: REG | E94: FR | F94: Marie | H94: Mail | I94: 46036 | J94: 46045 | K94: 46045 | L94: =IF(_xlfn.XLOOKUP(D94, ABZ!A:A, ABZ!B:B, "", 0) = 0, "", _xlfn.XLOOKUP(D94, ABZ!A:A, ABZ!B:B, "", 0)) -> D2C Ecommerce | M94: ausgecheckt | N94: Hme | O94: Z:\Produkte\Texte Web, Marketing, etc\deutsch\2026.01 | P94: Vertrieb
A95: MyFapp_20260115-de.xliff | B95: 11873 | D95: TBh | E95: DE | G95: Franziska | H95: jazz | I95: 46037 | J95: 46038 | K95: 46038 | L95: =IF(_xlfn.XLOOKUP(D95, ABZ!A:A, ABZ!B:B, "", 0) = 0, "", _xlfn.XLOOKUP(D95, ABZ!A:A, ABZ!B:B, "", 0)) -> User Interface & Clients | M95: geliefert | N95: FSc | O95: Z:\Produkte\F!Apps\FappMyF\GUI\iOS\deutsch\2026.01 | P95: Vertrieb
A96: Amazon_Content_Rest-de.docx | B96: 4309 | D96: JBL | E96: EN | F96: John | H96: Mail | I96: 46037 | J96: 46042 | K96: 46042 | L96: =IF(_xlfn.XLOOKUP(D96, ABZ!A:A, ABZ!B:B, "", 0) = 0, "", _xlfn.XLOOKUP(D96, ABZ!A:A, ABZ!B:B, "", 0)) -> D2C Ecommerce | M96: geliefert | N96: FSc | O96: Z:\Produkte\D2C\deutsch\2026.01 | P96: Vertrieb
A97: Amazon_Content_Rest-de.docx | B97: 4309 | D97: JBl | E97: Es | F97: Alba | H97: Mail | I97: 46037 | J97: 46042 | K97: 46042 | L97: =IF(_xlfn.XLOOKUP(D97, ABZ!A:A, ABZ!B:B, "", 0) = 0, "", _xlfn.XLOOKUP(D97, ABZ!A:A, ABZ!B:B, "", 0)) -> D2C Ecommerce | M97: geliefert | N97: FSc | O97: Z:\Produkte\D2C\deutsch\2026.01 | P97: Vertrieb
A98: Amazon_Content_Rest-de.docx | B98: 4309 | D98: JBl | E98: Fr | F98: Marie | H98: Mail | I98: 46037 | J98: 46042 | K98: 46042 | L98: =IF(_xlfn.XLOOKUP(D98, ABZ!A:A, ABZ!B:B, "", 0) = 0, "", _xlfn.XLOOKUP(D98, ABZ!A:A, ABZ!B:B, "", 0)) -> D2C Ecommerce | M98: geliefert | N98: FSc | O98: Z:\Produkte\D2C\deutsch\2026.01 | P98: Vertrieb
A99: Amazon_Content_Rest-de.docx | B99: 4309 | D99: JBl | E99: It | F99: Cristina | H99: Mail | I99: 46037 | J99: 46042 | K99: 46042 | L99: =IF(_xlfn.XLOOKUP(D99, ABZ!A:A, ABZ!B:B, "", 0) = 0, "", _xlfn.XLOOKUP(D99, ABZ!A:A, ABZ!B:B, "", 0)) -> D2C Ecommerce | M99: geliefert | N99: FSc | O99: Z:\Produkte\D2C\deutsch\2026.01 | P99: Support
A100: Amazon_Content_Rest-de.docx | B100: 4309 | D100: JBl | E100: Nl | F100: Angelique | H100: Mail | I100: 46037 | J100: 46042 | K100: 46042 | L100: =IF(_xlfn.XLOOKUP(D100, ABZ!A:A, ABZ!B:B, "", 0) = 0, "", _xlfn.XLOOKUP(D100, ABZ!A:A, ABZ!B:B, "", 0)) -> D2C Ecommerce | M100: geliefert | N100: FSc | O100: Z:\Produkte\D2C\deutsch\2026.01
A101: Amazon_Content_Rest-de.docx | B101: 4309 | D101: JBl | E101: Pl | F101: Yabylon | H101: Mail | I101: 46037 | J101: 46043 | K101: 46043 | L101: =IF(_xlfn.XLOOKUP(D101, ABZ!A:A, ABZ!B:B, "", 0) = 0, "", _xlfn.XLOOKUP(D101, ABZ!A:A, ABZ!B:B, "", 0)) -> D2C Ecommerce | M101: geliefert | N101: FSc | O101: Z:\Produkte\D2C\deutsch\2026.01
A102: Übersetzung Warenkorb Reminder-de.docx | B102: 115 | D102: Atc | E102: EN | F102: John | H102: Mail | I102: 46037 | J102: 46044 | K102: 46044 | L102: =IF(_xlfn.XLOOKUP(D102, ABZ!A:A, ABZ!B:B, "", 0) = 0, "", _xlfn.XLOOKUP(D102, ABZ!A:A, ABZ!B:B, "", 0)) -> D2C Ecommerce | M102: geliefert | N102: Hme | O102: Z:\Produkte\Texte Web, Marketing, etc\deutsch\2026.01
A103: Übersetzung Warenkorb Reminder-de.docx | B103: 115 | D103: Atc | E103: IT | F103: Cristina | G103: Laura | H103: Mail | I103: 46037 | J103: 46044 | K103: 46044 | L103: =IF(_xlfn.XLOOKUP(D103, ABZ!A:A, ABZ!B:B, "", 0) = 0, "", _xlfn.XLOOKUP(D103, ABZ!A:A, ABZ!B:B, "", 0)) -> D2C Ecommerce | M103: geliefert | N103: Hme | O103: Z:\Produkte\Texte Web, Marketing, etc\italienisch\2026.01
A104: Übersetzung Warenkorb Reminder-de.docx | B104: 115 | D104: Atc | E104: NL | F104: Angelique | H104: Mail | I104: 46037 | J104: 46044 | K104: 46044 | L104: =IF(_xlfn.XLOOKUP(D104, ABZ!A:A, ABZ!B:B, "", 0) = 0, "", _xlfn.XLOOKUP(D104, ABZ!A:A, ABZ!B:B, "", 0)) -> D2C Ecommerce | M104: geliefert | N104: Hme | O104: Z:\Produkte\Texte Web, Marketing, etc\deutsch\2026.01
A105: Übersetzung Warenkorb Reminder-de.docx | B105: 115 | D105: Atc | E105: ES | F105: Alba | H105: Mail | I105: 46037 | J105: 46044 | K105: 46044 | L105: =IF(_xlfn.XLOOKUP(D105, ABZ!A:A, ABZ!B:B, "", 0) = 0, "", _xlfn.XLOOKUP(D105, ABZ!A:A, ABZ!B:B, "", 0)) -> D2C Ecommerce | M105: geliefert | N105: Hme | O105: Z:\Produkte\Texte Web, Marketing, etc\deutsch\2026.01
A106: 4442_nl-NL_produktvergleich_20260116-124329.xml | B106: 102 | D106: PSe | E106: NL | F106: Angelique | H106: Mail | I106: 46038 | J106: 46050 | K106: 46052 | L106: =IF(_xlfn.XLOOKUP(D106, ABZ!A:A, ABZ!B:B, "", 0) = 0, "", _xlfn.XLOOKUP(D106, ABZ!A:A, ABZ!B:B, "", 0)) -> Channel Sales | M106: geliefert | N106: Hme | O106: Z:\Produkte\Texte Web, Marketing, etc\deutsch\2026.01
A107: dsgvo-loeschanfrage-d2c-daten | B107: 131 | D107: Jks | E107: EN | F107: Lisa | H107: Mail | I107: 46038 | J107: 46043 | K107: 46043 | L107: =IF(_xlfn.XLOOKUP(D107, ABZ!A:A, ABZ!B:B, "", 0) = 0, "", _xlfn.XLOOKUP(D107, ABZ!A:A, ABZ!B:B, "", 0)) -> Kundenservice | M107: geliefert | N107: Rho | O107: Z:\Produkte\Support-Aufträge\01.202616.01.26
A108: dsgvo-loeschanfrage-d2c-daten | B108: 131 | D108: Jks | E108: IT | F108: Laura | H108: Mail | I108: 46038 | J108: 46043 | K108: 46043 | L108: =IF(_xlfn.XLOOKUP(D108, ABZ!A:A, ABZ!B:B, "", 0) = 0, "", _xlfn.XLOOKUP(D108, ABZ!A:A, ABZ!B:B, "", 0)) -> Kundenservice | M108: geliefert | N108: Rho | O108: Z:\Produkte\Support-Aufträge\01.202616.01.26
...

Sheet ABZ
A1: ADo | B1: User Interface & Clients | C1: Development & Production
A2: AGi | B2: Channel Sales | C2: Sales & Communication
A3: AJA | B3: D2C Ecommerce | C3: Sales & Communication
A4: AKh | B4: Corporate Communications | C4: Sales & Communication
A5: AKU | B5: Technical Communication | C5: Support
A6: ALb | B6: User Interface & Clients | C6: Development & Production
A7: ALe | B7: Vertriebscontrolling | C7: Finance & Corporates
A8: ALi | B8: Finance | C8: Finance & Corporates
A9: ALp | B9: Corporate Communications | C9: Sales & Communication
A10: APa | B10: Sales Marketing | C10: Sales & Communication
A11: ASr | B11: Provider Sales | C11: Sales & Communication
A12: ATc | B12: D2C Ecommerce | C12: Sales & Communication
... A134: YKo | B134: Human Resources | C134: Finance & Corporates

Sheet 2025
A1: Aufträge | B1: Vom | C1: Sprache | D1: Verantwortlich | E1: Jazz | F1: Ablageort | G1: Datum | H1: Lieferung | I1: Deadline | J1: Abteilung | K1: Status
A3: API-Reference-de.docx | B3: TKO | C3: EN | D3: Joe | E3: Mail | F3: Z:\Produkte\Texte Web, Marketing, etc\deutsch\2025.01 | G3: 45660 | H3: 45664 | I3: 45665 | J3: =IF(_xlfn.XLOOKUP(B3, ABZ!A:A, ABZ!B:B, "", 0) = 0, "", _xlfn.XLOOKUP(B3, ABZ!A:A, ABZ!B:B, "", 0)) -> Technical Communication
A4: access-link-delivery-repeater-template_de.properties | B4: MxG | C4: En | D4: Susan | E4: 137117 | F4: Z:\Produkte\MyFRITZ\deutsch\2024.12\MeshSetUebersetzung\Cloud-Mailing | G4: 45660 | H4: 45663 | I4: 45667 | J4: =IF(_xlfn.XLOOKUP(B4, ABZ!A:A, ABZ!B:B, "", 0) = 0, "", _xlfn.XLOOKUP(B4, ABZ!A:A, ABZ!B:B, "", 0)) -> IT
A5: access-link-delivery-repeater-template_de.properties | B5: MxG | C5: Es | D5: Helena | E5: 137117 | F5: Z:\Produkte\MyFRITZ\deutsch\2024.12\MeshSetUebersetzung\Cloud-Mailing | G5: 45660 | H5: 45670 | I5: 45667 | J5: =IF(_xlfn.XLOOKUP(B5, ABZ!A:A, ABZ!B:B, "", 0) = 0, "", _xlfn.XLOOKUP(B5, ABZ!A:A, ABZ!B:B, "", 0)) -> IT
A6: access-link-delivery-repeater-template_de.properties | B6: MxG | C6: Fr | D6: Marie/Martine | E6: 137117 | F6: Z:\Produkte\MyFRITZ\deutsch\2024.12\MeshSetUebersetzung\Cloud-Mailing | G6: 45660 | H6: 45664 | I6: 45667 | J6: =IF(_xlfn.XLOOKUP(B6, ABZ!A:A, ABZ!B:B, "", 0) = 0, "", _xlfn.XLOOKUP(B6, ABZ!A:A, ABZ!B:B, "", 0)) -> IT
A7: access-link-delivery-repeater-template_de.properties | B7: MxG | C7: It | D7: Laura | E7: 137117 | F7: Z:\Produkte\MyFRITZ\deutsch\2024.12\MeshSetUebersetzung\Cloud-Mailing | G7: 45660 | H7: 45300 | I7: 45667 | J7: =IF(_xlfn.XLOOKUP(B7, ABZ!A:A, ABZ!B:B, "", 0) = 0, "", _xlfn.XLOOKUP(B7, ABZ!A:A, ABZ!B:B, "", 0)) -> IT
A8: access-link-delivery-repeater-template_de.properties | B8: MxG | C8: Nl | D8: Angelique | E8: 137117 | F8: Z:\Produkte\MyFRITZ\deutsch\2024.12\MeshSetUebersetzung\Cloud-Mailing | G8: 45660 | H8: 45666 | I8: 45667 | J8: =IF(_xlfn.XLOOKUP(B8, ABZ!A:A, ABZ!B:B, "", 0) = 0, "", _xlfn.XLOOKUP(B8, ABZ!A:A, ABZ!B:B, "", 0)) -> IT
A9: botnet-detected-notification-repeater-template_de.properties | B9: MxG | C9: En | D9: Susan | E9: 137117 | F9: Z:\Produkte\MyFRITZ\deutsch\2024.12\MeshSetUebersetzung\Cloud-Mailing | G9: 45660 | H9: 45663 | I9: 45667 | J9: =IF(_xlfn.XLOOKUP(B9, ABZ!A:A, ABZ!B:B, "", 0) = 0, "", _xlfn.XLOOKUP(B9, ABZ!A:A, ABZ!B:B, "", 0)) -> IT
A10: botnet-detected-notification-repeater-template_de.properties | B10: MxG | C10: Es | D10: Helena | E10: 137117 | F10: Z:\Produkte\MyFRITZ\deutsch\2024.12\MeshSetUebersetzung\Cloud-Mailing | G10: 45660 | H10: 45670 | I10: 45667 | J10: =IF(_xlfn.XLOOKUP(B10, ABZ!A:A, ABZ!B:B, "", 0) = 0, "", _xlfn.XLOOKUP(B10, ABZ!A:A, ABZ!B:B, "", 0)) -> IT
A11: botnet-detected-notification-repeater-template_de.properties | B11: MxG | C11: Fr | D11: Marie/Martine | E11: 137117 | F11: Z:\Produkte\MyFRITZ\deutsch\2024.12\MeshSetUebersetzung\Cloud-Mailing | G11: 45660 | H11: 45664 | I11: 45667 | J11: =IF(_xlfn.XLOOKUP(B11, ABZ!A:A, ABZ!B:B, "", 0) = 0, "", _xlfn.XLOOKUP(B11, ABZ!A:A, ABZ!B:B, "", 0)) -> IT
A12: botnet-detected-notification-repeater-template_de.properties | B12: MxG | C12: It | D12: Laura | E12: 137117 | F12: Z:\Produkte\MyFRITZ\deutsch\2024.12\MeshSetUebersetzung\Cloud-Mailing | G12: 45660 | H12: 45300 | I12: 45667 | J12: =IF(_xlfn.XLOOKUP(B12, ABZ!A:A, ABZ!B:B, "", 0) = 0, "", _xlfn.XLOOKUP(B12, ABZ!A:A, ABZ!B:B, "", 0)) -> IT
A13: botnet-detected-notification-repeater-template_de.properties | B13: MxG | C13: Nl | D13: Angelique | E13: 137117 | F13: Z:\Produkte\MyFRITZ\deutsch\2024.12\MeshSetUebersetzung\Cloud-Mailing | G13: 45660 | H13: 45666 | I13: 45667 | J13: =IF(_xlfn.XLOOKUP(B13, ABZ!A:A, ABZ!B:B, "", 0) = 0, "", _xlfn.XLOOKUP(B13, ABZ!A:A, ABZ!B:B, "", 0)) -> IT
A14: confirm-box-repeater_de.properties | B14: MxG | C14: En | D14: Susan | E14: 137117 | F14: Z:\Produkte\MyFRITZ\deutsch\2024.12\MeshSetUebersetzung\Box-Management | G14: 45660 | H14: 45663 | I14: 45667 | J14: =IF(_xlfn.XLOOKUP(B14, ABZ!A:A, ABZ!B:B, "", 0) = 0, "", _xlfn.XLOOKUP(B14, ABZ!A:A, ABZ!B:B, "", 0)) -> IT
A15: confirm-box-repeater_de.properties | B15: MxG | C15: Es | D15: Helena | E15: 137117 | F15: Z:\Produkte\MyFRITZ\deutsch\2024.12\MeshSetUebersetzung\Box-Management | G15: 45660 | H15: 45670 | I15: 45667 | J15: =IF(_xlfn.XLOOKUP(B15, ABZ!A:A, ABZ!B:B, "", 0) = 0, "", _xlfn.XLOOKUP(B15, ABZ!A:A, ABZ!B:B, "", 0)) -> IT
... A83: update-succeeded-notification-repeater-template_de.properties | B83: MxG | C83: Nl | D83: Angelique | E83: 137117 | F83: Z:\Produkte\MyFRITZ\deutsch\2024.12\MeshSetUebersetzung\Cloud-Mailing | G83: 45660 | H83: 45666 | I83: 45667 | J83: =IF(_xlfn.XLOOKUP(B83, ABZ!A:A, ABZ!B:B, "", 0) = 0, "", _xlfn.XLOOKUP(B83, ABZ!A:A, ABZ!B:B, "", 0)) -> IT
A85: Gewinnerbenachrichtigung-Du-Form-de.docx | B85: Pse | C85: NL | D85: Angelique | F85: Z:\Produkte\Texte Web, Marketing, etc\deutsch\2025.01 | G85: 45665 | H85: 45667 | J85: =IF(_xlfn.XLOOKUP(B85, ABZ!A:A, ABZ!B:B, "", 0) = 0, "", _xlfn.XLOOKUP(B85, ABZ!A:A, ABZ!B:B, "", 0)) -> Channel Sales
A86: Gewinnerbenachrichtigung-Du-Form-de.docx | B86: Pse | C86: ES | D86: Marta/Helena | F86: Z:\Produkte\Texte Web, Marketing, etc\deutsch\2025.01 | G86: 45665 | H86: 45667 | J86: =IF(_xlfn.XLOOKUP(B86, ABZ!A:A, ABZ!B:B, "", 0) = 0, "", _xlfn.XLOOKUP(B86, ABZ!A:A, ABZ!B:B, "", 0)) -> Channel Sales
A87: Gewinnerbenachrichtigung-Du-Form-de.docx | B87: Pse | C87: IT | D87: Crisitna/Laura | F87: Z:\Produkte\Texte Web, Marketing, etc\deutsch\2025.01 | G87: 45665 | H87: 45301 | J87: =IF(_xlfn.XLOOKUP(B87, ABZ!A:A, ABZ!B:B, "", 0) = 0, "", _xlfn.XLOOKUP(B87, ABZ!A:A, ABZ!B:B, "", 0)) -> Channel Sales
A88: Newsletter ES Jan25.docx | B88: Jwg | C88: ES | D88: Marta/Helena | F88: Z:\Produkte\Texte Web, Marketing, etc\deutsch\2025.01 | G88: 45665 | H88: 45670 | I88: 45671 | J88: =IF(_xlfn.XLOOKUP(B88, ABZ!A:A, ABZ!B:B, "", 0) = 0, "", _xlfn.XLOOKUP(B88, ABZ!A:A, ABZ!B:B, "", 0)) -> Channel Sales
A89: FR_Amazon_Brand_Store_Texte_Übersetzungsbüro.docx | B89: apa | C89: FR | D89: Marie | F89: Z:\Produkte\Texte Web, Marketing, etc\deutsch\2025.01 | G89: 45666 | H89: 45674 | I89: 45672 | J89: =IF(_xlfn.XLOOKUP(B89, ABZ!A:A, ABZ!B:B, "", 0) = 0, "", _xlfn.XLOOKUP(B89, ABZ!A:A, ABZ!B:B, "", 0)) -> Sales Marketing
A90: 20241203_Provider International Pitch_1-16-de.pptx | B90: PWI | C90: EN | D90: Susan | F90: Z:\Produkte\Texte Web, Marketing, etc\deutsch\2025.01 | G90: 45667 | H90: 45670 | I90: 45671 | J90: =IF(_xlfn.XLOOKUP(B90, ABZ!A:A, ABZ!B:B, "", 0) = 0, "", _xlfn.XLOOKUP(B90, ABZ!A:A, ABZ!B:B, "", 0)) -> Sales Marketing
A91: Mesh Set 3000_[DE-Vorlage].idml | B91: Ost | C91: EN | D91: Susan | F91: Z:\Produkte\F!WLAN Repeater\Mesh Set 3000 (1200 AX)\international\2025.01\UeM | G91: 45667 | H91: 45670 | I91: 45672 | J91: =IF(_xlfn.XLOOKUP(B91, ABZ!A:A, ABZ!B:B, "", 0) = 0, "", _xlfn.XLOOKUP(B91, ABZ!A:A, ABZ!B:B, "", 0)) -> Technical Communication
A92: Mesh Set 3000_[DE-Vorlage].idml | B92: Ost | C92: FR | D92: Marie | F92: Z:\Produkte\F!WLAN Repeater\Mesh Set 3000 (1200 AX)\international\2025.01\UeM | G92: 45667 | H92: 45670 | I92: 45672 | J92: =IF(_xlfn.XLOOKUP(B92, ABZ!A:A, ABZ!B:B, "", 0) = 0, "", _xlfn.XLOOKUP(B92, ABZ!A:A, ABZ!B:B, "", 0)) -> Technical Communication
A93: Mesh Set 3000_[DE-Vorlage].idml | B93: Ost | C93: ES | D93: Helena | F93: Z:\Produkte\F!WLAN Repeater\Mesh Set 3000 (1200 AX)\international\2025.01\UeM | G93: 45667 | I93: 45672 | J93: =IF(_xlfn.XLOOKUP(B93, ABZ!A:A, ABZ!B:B, "", 0) = 0, "", _xlfn.XLOOKUP(B93, ABZ!A:A, ABZ!B:B, "", 0)) -> Technical Communication
A94: Mesh Set 3000_[DE-Vorlage].idml | B94: Ost | C94: IT | D94: Laura | F94: Z:\Produkte\F!WLAN Repeater\Mesh Set 3000 (1200 AX)\international\2025.01\UeM | G94: 45667 | H94: 45670 | I94: 45672 | J94: =IF(_xlfn.XLOOKUP(B94, ABZ!A:A, ABZ!B:B, "", 0) = 0, "", _xlfn.XLOOKUP(B94, ABZ!A:A, ABZ!B:B, "", 0)) -> Technical Communication
A95: Mesh Set 3000_[DE-Vorlage].idml | B95: Ost | C95: NL | D95: Angelique | F95: Z:\Produkte\F!WLAN Repeater\Mesh Set 3000 (1200 AX)\international\2025.01\UeM | G95: 45667 | H95: 45672 | I95: 45672 | J95: =IF(_xlfn.XLOOKUP(B95, ABZ!A:A, ABZ!B:B, "", 0) = 0, "", _xlfn.XLOOKUP(B95, ABZ!A:A, ABZ!B:B, "", 0)) -> Technical Communication
A96: Master_HB_Frep_MeshSet_V4-2025-01-10_D-00000082_T-00000762_EngineeringModules_de-DE_en-US.xml | B96: Cmi | C96: EN | D96: Susan | E96: Mail | F96: Z:\International\Tico\work\2025-01-10_D-00000082_T-00000762_de-DE_en-US.xml\untranslated | G96: 45667 | H96: 45670 | I96: 45684 | J96: =IF(_xlfn.XLOOKUP(B96, ABZ!A:A, ABZ!B:B, "", 0) = 0, "", _xlfn.XLOOKUP(B96, ABZ!A:A, ABZ!B:B, "", 0)) -> Technical Communication
A97: Master_HB_Frep_MeshSet_V4-2025-01-10_D-00000082_T-00000765_EngineeringModules_de-DE_it-IT.Fragments.xml | B97: Cmi | C97: IT | D97: Laura | E97: Mail | F97: Z:\International\Tico\work\2025-01-10_D-00000082_T-00000765_de-DE_it-IT.xml\untranslated | G97: 45667 | H97: 45686 | I97: 45684 | J97: =IF(_xlfn.XLOOKUP(B97, ABZ!A:A, ABZ!B:B, "", 0) = 0, "", _xlfn.XLOOKUP(B97, ABZ!A:A, ABZ!B:B, "", 0)) -> Technical Communication
A98: Master_HB_Frep_MeshSet_V4-2025-01-10_D-00000082_T-00000765_EngineeringModules_de-DE_it-IT.xml | B98: Cmi | C98: IT | D98: Laura | E98: Mail | F98: Z:\International\Tico\work\2025-01-10_D-00000082_T-00000765_de-DE_it-IT.xml\untranslated | G98: 45667 | H98: 45686 | I98: 45684 | J98: =IF(_xlfn.XLOOKUP(B98, ABZ!A:A, ABZ!B:B, "", 0) = 0, "", _xlfn.XLOOKUP(B98, ABZ!A:A, ABZ!B:B, "", 0)) -> Technical Communication
A99: Master_HB_Frep_MeshSet_V4-2025-01-10_D-00000082_T-00000764_EngineeringModules_de-DE_es-ES.xml | B99: Cmi | C99: ES | D99: Helena | E99: Mail | F99: Z:\International\Tico\work\2025-01-10_D-00000082_T-00000764_de-DE_es-ES.xml\untranslated | G99: 45667 | I99: 45684 | J99: =IF(_xlfn.XLOOKUP(B99, ABZ!A:A, ABZ!B:B, "", 0) = 0, "", _xlfn.XLOOKUP(B99, ABZ!A:A, ABZ!B:B, "", 0)) -> Technical Communication
A100: Master_HB_Frep_MeshSet_V4-2025-01-10_D-00000082_T-00000763_EngineeringModules_de-DE_fr-FR.xml | B100: Cmi | C100: FR | D100: Martine | E100: Mail | F100: Z:\International\Tico\work\2025-01-10_D-00000082_T-00000763_de-DE_fr-FR.xml\untranslated | G100: 45667 | H100: 45670 | I100: 45684 | J100: =IF(_xlfn.XLOOKUP(B100, ABZ!A:A, ABZ!B:B, "", 0) = 0, "", _xlfn.XLOOKUP(B100, ABZ!A:A, ABZ!B:B, "", 0)) -> Technical Communication
A101: Master_HB_Frep_MeshSet_V4-2025-01-10_D-00000082_T-00000766_EngineeringModules_de-DE_nl-NL.xml | B101: Cmi | C101: NL | D101: Angelique | E101: Mail | F101: Z:\International\Tico\work\2025-01-10_D-00000082_T-00000766_de-DE_nl-NL.xml\untranslated | G101: 45667 | H101: 45672 | I101: 45684 | J101: =IF(_xlfn.XLOOKUP(B101, ABZ!A:A, ABZ!B:B, "", 0) = 0, "", _xlfn.XLOOKUP(B101, ABZ!A:A, ABZ!B:B, "", 0)) -> Technical Communication
A102: Newsletter 01_2025-de-nl.docx | B102: PSe | C102: De | D102: Franziska | E102: Mail | F102: Z:\Produkte\Texte Web, Marketing, etc\deutsch\2025.01 | G102: 45670 | H102: 45670 | I102: 45670 | J102: =IF(_xlfn.XLOOKUP(B102, ABZ!A:A, ABZ!B:B, "", 0) = 0, "", _xlfn.XLOOKUP(B102, ABZ!A:A, ABZ!B:B, "", 0)) -> Channel Sales
A103: Newsletter 01_2025-de-nl.docx | B103: PSe | C103: Nl | D103: Angelique | E103: Mail | F103: Z:\Produkte\Texte Web, Marketing, etc\deutsch\2025.01 | G103: 45670 | H103: 45670 | I103: 45670 | J103: =IF(_xlfn.XLOOKUP(B103, ABZ!A:A, ABZ!B:B, "", 0) = 0, "", _xlfn.XLOOKUP(B103, ABZ!A:A, ABZ!B:B, "", 0)) -> Channel Sales
A104: Januar-Newsletter Österreich | B104: PSe | C104: De | D104: Franziska | E104: Mail | G104: 45670 | H104: 45670 | I104: 45670 | J104: =IF(_xlfn.XLOOKUP(B104, ABZ!A:A, ABZ!B:B, "", 0) = 0, "", _xlfn.XLOOKUP(B104, ABZ!A:A, ABZ!B:B, "", 0)) -> Channel Sales
A105: Januar-Newsletter Schweiz | B105: PSe | C105: De | D105: Franziska | E105: Mail | G105: 45670 | H105: 45670 | I105: 45670 | J105: =IF(_xlfn.XLOOKUP(B105, ABZ!A:A, ABZ!B:B, "", 0) = 0, "", _xlfn.XLOOKUP(B105, ABZ!A:A, ABZ!B:B, "", 0)) -> Channel Sales
A106: Kick-off_2025-de-en.docx | B106: AGi | C106: De | D106: Franziska | E106: Mail | F106: Z:\Produkte\Texte Web, Marketing, etc\deutsch\2025.01 | G106: 45671 | H106: 45671 | I106: 45671 | J106: =IF(_xlfn.XLOOKUP(B106, ABZ!A:A, ABZ!B:B, "", 0) = 0, "", _xlfn.XLOOKUP(B106, ABZ!A:A, ABZ!B:B, "", 0)) -> Channel Sales
A107: Kick-off_2025-de-en.docx | B107: AGi | C107: En | D107: Susan | E107: Mail | F107: Z:\Produkte\Texte Web, Marketing, etc\deutsch\2025.01 | G107: 45671 | H107: 45671 | I107: 45671 | J107: =IF(_xlfn.XLOOKUP(B107, ABZ!A:A, ABZ!B:B, "", 0) = 0, "", _xlfn.XLOOKUP(B107, ABZ!A:A, ABZ!B:B, "", 0)) -> Channel Sales
A108: Master_OLH_F!MeshSet_v3-2025-01-14_D-00000080_T-00000770_EngineeringModules_de-DE_it-IT.xml | B108: Cmi | C108: IT | D108: Laura | E108: Mail | F108: Z:\International\Tico\work\2025-01-14_D-00000080_T-00000770_de-DE_it-IT.xml\untranslated | G108: 45671 | H108: 45688 | I108: 45680 | J108: =IF(_xlfn.XLOOKUP(B108, ABZ!A:A, ABZ!B:B, "", 0) = 0, "", _xlfn.XLOOKUP(B108, ABZ!A:A, ABZ!B:B, "", 0)) -> Technical Communication
A109: Master_OLH_F!MeshSet_v3-2025-01-14_D-00000080_T-00000771_EngineeringModules_de-DE_nl-NL.xml | B109: Cmi | C109: NL | D109: Angelique | E109: Mail | F109: Z:\International\Tico\work\2025-01-14_D-00000080_T-00000771_de-DE_nl-NL.xml\untranslated | G109: 45671 | H109: 45680 | I109: 45680 | J109: =IF(_xlfn.XLOOKUP(B109, ABZ!A:A, ABZ!B:B, "", 0) = 0, "", _xlfn.XLOOKUP(B109, ABZ!A:A, ABZ!B:B, "", 0)) -> Technical Communication
A110: Master_OLH_F!MeshSet_v3-2025-01-14_D-00000080_T-00000769_EngineeringModules_de-DE_es-ES.xml | B110: Cmi | C110: ES | D110: Helena | E110: Mail | F110: Z:\International\Tico\work\2025-01-14_D-00000080_T-00000769_de-DE_es-ES.xml\untranslated | G110: 45671 | H110: 45685 | I110: 45680 | J110: =IF(_xlfn.XLOOKUP(B110, ABZ!A:A, ABZ!B:B, "", 0) = 0, "", _xlfn.XLOOKUP(B110, ABZ!A:A, ABZ!B:B, "", 0)) -> Technical Communication
A111: Master_OLH_F!MeshSet_v3-2025-01-14_D-00000080_T-00000768_EngineeringModules_de-DE_fr-FR.xml | B111: Cmi | C111: FR | D111: Martine | E111: Mail | F111: Z:\International\Tico\work\2025-01-14_D-00000080_T-00000768_de-DE_fr-FR.xml\untranslated | G111: 45671 | H111: 45679 | I111: 45680 | J111: =IF(_xlfn.XLOOKUP(B111, ABZ!A:A, ABZ!B:B, "", 0) = 0, "", _xlfn.XLOOKUP(B111, ABZ!A:A, ABZ!B:B, "", 0)) -> Technical Communication
A112: Master_OLH_F!MeshSet_v3-2025-01-14_D-00000080_T-00000767_EngineeringModules_de-DE_en-US.xml | B112: Cmi | C112: EN | D112: Susan | E112: Mail | F112: Z:\International\Tico\work\2025-01-14_D-00000080_T-00000767_de-DE_en-US.xml\untranslated | G112: 45671 | H112: 45677 | I112: 45680 | J112: =IF(_xlfn.XLOOKUP(B112, ABZ!A:A, ABZ!B:B, "", 0) = 0, "", _xlfn.XLOOKUP(B112, ABZ!A:A, ABZ!B:B, "", 0)) -> Technical Communication
A113: Newsletter_01_2025_de-it.docx | B113: JWg | C113: De | D113: Franziska | E113: Mail | F113: Z:\Produkte\Texte Web, Marketing, etc\deutsch\2025.01 | G113: 45672 | H113: 45672 | I113: 45672 | J113: =IF(_xlfn.XLOOKUP(B113, ABZ!A:A, ABZ!B:B, "", 0) = 0, "", _xlfn.XLOOKUP(B113, ABZ!A:A, ABZ!B:B, "", 0)) -> Channel Sales
A114: Newsletter_01_2025_de-it.docx | B114: JWg | C114: It | D114: Cristina/Laura | E114: Mail | F114: Z:\Produkte\Texte Web, Marketing, etc\italienisch\2025.01 | G114: 45672 | H114: 45674 | I114: 45678 | J114: =IF(_xlfn.XLOOKUP(B114, ABZ!A:A, ABZ!B:B, "", 0) = 0, "", _xlfn.XLOOKUP(B114, ABZ!A:A, ABZ!B:B, "", 0)) -> Channel Sales
A115: FB_post_12-1057-1-9-de.docx | B115: ALb | C115: En | D115: Susan | E115: Mail | F115: Z:\Produkte\F!Box allgemein\GUI-alt\deutsch\2025.01 | G115: 45672 | H115: 45673 | I115: 45674 | J115: =IF(_xlfn.XLOOKUP(B115, ABZ!A:A, ABZ!B:B, "", 0) = 0, "", _xlfn.XLOOKUP(B115, ABZ!A:A, ABZ!B:B, "", 0)) -> User Interface & Clients
A116: FB_post_12-1057-1-9-de.docx | B116: ALb | C116: Es | D116: Helena | E116: Mail | F116: Z:\Produkte\F!Box allgemein\GUI-alt\deutsch\2025.01 | G116: 45672 | H116: 45672 | I116: 45674 | J116: =IF(_xlfn.XLOOKUP(B116, ABZ!A:A, ABZ!B:B, "", 0) = 0, "", _xlfn.XLOOKUP(B116, ABZ!A:A, ABZ!B:B, "", 0)) -> User Interface & Clients
A117: FB_post_12-1057-1-9-de.docx | B117: ALb | C117: Fr | D117: Marie/Martine | E117: Mail | F117: Z:\Produkte\F!Box allgemein\GUI-alt\deutsch\2025.01 | G117: 45672 | H117: 45673 | I117: 45674 | J117: =IF(_xlfn.XLOOKUP(B117, ABZ!A:A, ABZ!B:B, "", 0) = 0, "", _xlfn.XLOOKUP(B117, ABZ!A:A, ABZ!B:B, "", 0)) -> User Interface & Clients
... A120: FB_post_12-1057-1-9-de.docx | B120: ALb | C120: Pl | D120: Yabylon | E120: Mail | F120: Z:\Produkte\F!Box allgemein\GUI-alt\deutsch\2025.01 | G120: 45672 | H120: 45674 | I120: 45674 | J120: =IF(_xlfn.XLOOKUP(B120, ABZ!A:A, ABZ!B:B, "", 0) = 0, "", _xlfn.XLOOKUP(B120, ABZ!A:A, ABZ!B:B, "", 0)) -> User Interface & Clients
A121: Booklet_350_[DE].idml | B121: Ost | C121: EN | D121: Susan | F121: Z:\Produkte\F!Smart Kurzanleitungen\Control 350\international\2025.01\UeM | G121: 45672 | H121: 45691 | I121: 45691 | J121: =IF(_xlfn.XLOOKUP(B121, ABZ!A:A, ABZ!B:B, "", 0) = 0, "", _xlfn.XLOOKUP(B121, ABZ!A:A, ABZ!B:B, "", 0)) -> Technical Communication
A122: Booklet_350_[DE].idml | B122: Ost | C122: FR | D122: Martine/Marie | F122: Z:\Produkte\F!Smart Kurzanleitungen\Control 350\international\2025.01\UeM | G122: 45672 | H122: 45691 | I122: 45691 | J122: =IF(_xlfn.XLOOKUP(B122, ABZ!A:A, ABZ!B:B, "", 0) = 0, "", _xlfn.XLOOKUP(B122, ABZ!A:A, ABZ!B:B, "", 0)) -> Technical Communication
A123: Booklet_350_[DE].idml | B123: Ost | C123: IT | D123: Laura | F123: Z:\Produkte\F!Smart Kurzanleitungen\Control 350\international\2025.01\UeM | G123: 45672 | H123: 45688 | I123: 45691 | J123: =IF(_xlfn.XLOOKUP(B123, ABZ!A:A, ABZ!B:B, "", 0) = 0, "", _xlfn.XLOOKUP(B123, ABZ!A:A, ABZ!B:B, "", 0)) -> Technical Communication
A124: Booklet_350_[DE].idml | B124: Ost | C124: ES | D124: Helena | F124: Z:\Produkte\F!Smart Kurzanleitungen\Control 350\international\2025.01\UeM | G124: 45672 | I124: 45691 | J124: =IF(_xlfn.XLOOKUP(B124, ABZ!A:A, ABZ!B:B, "", 0) = 0, "", _xlfn.XLOOKUP(B124, ABZ!A:A, ABZ!B:B, "", 0)) -> Technical Communication
A125: Booklet_350_[DE].idml | B125: Ost | C125: NL | D125: Angelique | F125: Z:\Produkte\F!Smart Kurzanleitungen\Control 350\international\2025.01\UeM | G125: 45672 | H125: 45325 | I125: 45691 | J125: =IF(_xlfn.XLOOKUP(B125, ABZ!A:A, ABZ!B:B, "", 0) = 0, "", _xlfn.XLOOKUP(B125, ABZ!A:A, ABZ!B:B, "", 0)) -> Technical Communication
A126: 2025-01-09_Wahlordnung_2025-de-en.docx | B126: ASr | C126: De | D126: Franziska | E126: Mail | F126: Z:\Produkte\Texte Web, Marketing, etc\deutsch\2025.01 | G126: 45673 | H126: 45673 | I126: 45673 | J126: =IF(_xlfn.XLOOKUP(B126, ABZ!A:A, ABZ!B:B, "", 0) = 0, "", _xlfn.XLOOKUP(B126, ABZ!A:A, ABZ!B:B, "", 0)) -> Provider Sales
A127: 2025-01-09_Wahlordnung_2025-de-en.docx | B127: ASr | C127: En | D127: Joe | E127: Mail | F127: Z:\Produkte\Texte Web, Marketing, etc\deutsch\2025.01 | G127: 45673 | H127: 45677 | I127: 45677 | J127: =IF(_xlfn.XLOOKUP(B127, ABZ!A:A, ABZ!B:B, "", 0) = 0, "", _xlfn.XLOOKUP(B127, ABZ!A:A, ABZ!B:B, "", 0)) -> Provider Sales
A128: 3606_nl-NL_fritz_der_freund_und_helfer_der_polizei_20250116-114517.xml | B128: PSe | C128: Nl | D128: Angelique | E128: Mail | F128: Z:\Produkte\Texte Web, Marketing, etc\deutsch\2025.01 | G128: 45673 | H128: 45688 | I128: 45688 | J128: =IF(_xlfn.XLOOKUP(B128, ABZ!A:A, ABZ!B:B, "", 0) = 0, "", _xlfn.XLOOKUP(B128, ABZ!A:A, ABZ!B:B, "", 0)) -> Channel Sales
A129: Mesh Set 3000_[DE-INT].indd | B129: Dha | C129: PT | D129: Yabylon | E129: Mail | F129: Z:\Produkte\F!WLAN Repeater\Mesh Set 3000 (1200 AX)\portugiesisch\2025.01 | G129: 45673 | H129: 45677 | I129: 45677 | J129: =IF(_xlfn.XLOOKUP(B129, ABZ!A:A, ABZ!B:B, "", 0) = 0, "", _xlfn.XLOOKUP(B129, ABZ!A:A, ABZ!B:B, "", 0)) -> Product Management
A130: Projektkonditionen-de.docx | B130: AGi | C130: NL | D130: Angelique | E130: Mail | F130: Z:\Produkte\Texte Web, Marketing, etc\deutsch\2025.01 | G130: 45667 | H130: 45674 | I130: 45674 | J130: =IF(_xlfn.XLOOKUP(B130, ABZ!A:A, ABZ!B:B, "", 0) = 0, "", _xlfn.XLOOKUP(B130, ABZ!A:A, ABZ!B:B, "", 0)) -> Channel Sales
A131: Projektkonditionen-de.docx | B131: AGi | C131: ES | D131: Helena | E131: Mail | F131: Z:\Produkte\Texte Web, Marketing, etc\deutsch\2025.01 | G131: 45667 | H131: 45674 | I131: 45674 | J131: =IF(_xlfn.XLOOKUP(B131, ABZ!A:A, ABZ!B:B, "", 0) = 0, "", _xlfn.XLOOKUP(B131, ABZ!A:A, ABZ!B:B, "", 0)) -> Channel Sales
A132: Projektkonditionen-de.docx | B132: AGi | C132: IT | D132: Laura | E132: Mail | F132: Z:\Produkte\Texte Web, Marketing, etc\italienisch\2025.01 | G132: 45667 | H132: 45674 | I132: 45674 | J132: =IF(_xlfn.XLOOKUP(B132, ABZ!A:A, ABZ!B:B, "", 0) = 0, "", _xlfn.XLOOKUP(B132, ABZ!A:A, ABZ!B:B, "", 0)) -> Channel Sales
A133: 3611_nl-NL_avm_wissensdatenbank_20250117-093832.xml | B133: PSe | C133: NL | D133: Angelique | E133: Mail | F133: Z:\Produkte\Texte Web, Marketing, etc\niederlaendisch\2025.01 | G133: 45674 | H133: 45688 | I133: 45688 | J133: =IF(_xlfn.XLOOKUP(B133, ABZ!A:A, ABZ!B:B, "", 0) = 0, "", _xlfn.XLOOKUP(B133, ABZ!A:A, ABZ!B:B, "", 0)) -> Channel Sales
A134: 3609_it-IT_avm_wissensdatenbank_20250117-093909.xml | B134: PSe | C134: IT | D134: Cristina/Laura | E134: Mail | F134: Z:\Produkte\Texte Web, Marketing, etc\italienisch\2025.01 | G134: 45674 | H134: 45688 | I134: 45688 | J134: =IF(_xlfn.XLOOKUP(B134, ABZ!A:A, ABZ!B:B, "", 0) = 0, "", _xlfn.XLOOKUP(B134, ABZ!A:A, ABZ!B:B, "", 0)) -> Channel Sales
A135: 3612_es-ES_avm_wissensdatenbank_20250117-094010.xml | B135: PSe | C135: ES | D135: Marta/Helena | E135: Mail | F135: Z:\Produkte\Texte Web, Marketing, etc\spanisch\2025.01 | G135: 45674 | H135: 45688 | I135: 45688 | J135: =IF(_xlfn.XLOOKUP(B135, ABZ!A:A, ABZ!B:B, "", 0) = 0, "", _xlfn.XLOOKUP(B135, ABZ!A:A, ABZ!B:B, "", 0)) -> Channel Sales
A136: AlpArray Voice Over.docx | B136: GPr | C136: NL | D136: Marion | E136: Mail | F136: Z:\Produkte\Texte Web, Marketing, etc\niederlaendisch\2025.01 | G136: 45674 | H136: 45684 | I136: 45700 | J136: =IF(_xlfn.XLOOKUP(B136, ABZ!A:A, ABZ!B:B, "", 0) = 0, "", _xlfn.XLOOKUP(B136, ABZ!A:A, ABZ!B:B, "", 0)) -> Sales Marketing
A137: FappBoxSetup_20250116-de.xliff | B137: KNu | C137: De | D137: Franziska | E137: 137614 | F137: Z:\Produkte\F!Apps\FappBoxSetup\deutsch\2025.01 | G137: 45673 | H137: 45674 | I137: 45674 | J137: =IF(_xlfn.XLOOKUP(B137, ABZ!A:A, ABZ!B:B, "", 0) = 0, "", _xlfn.XLOOKUP(B137, ABZ!A:A, ABZ!B:B, "", 0)) -> User Interface & Clients
A138: MyFapp_20251601-de.xliff | B138: KNu | C138: De | D138: Franziska | E138: 137963 | F138: Z:\Produkte\F!Apps\FappMyF\GUI\iOS\deutsch\2025.01 | G138: 45673 | H138: 45674 | I138: 45674 | J138: =IF(_xlfn.XLOOKUP(B138, ABZ!A:A, ABZ!B:B, "", 0) = 0, "", _xlfn.XLOOKUP(B138, ABZ!A:A, ABZ!B:B, "", 0)) -> User Interface & Clients
A139: einladung_MWC_2025_de | B139: Bal | C139: EN | D139: Susan | F139: Z:\Produkte\Texte Web, Marketing, etc\deutsch\2025.01 | G139: 45677 | H139: 44216 | I139: 45677 | J139: =IF(_xlfn.XLOOKUP(B139, ABZ!A:A, ABZ!B:B, "", 0) = 0, "", _xlfn.XLOOKUP(B139, ABZ!A:A, ABZ!B:B, "", 0)) -> Corporate Communications
A140: 20250114_Ankuendigung_AVM_Mesh Set 4200_Edition_INT_DE_Final.docx | B140: APa | C140: De | D140: Franziska | F140: Z:\Produkte\Texte Web, Marketing, etc\deutsch\2025.01 | G140: 45677 | H140: 45677 | I140: 45677 | J140: =IF(_xlfn.XLOOKUP(B140, ABZ!A:A, ABZ!B:B, "", 0) = 0, "", _xlfn.XLOOKUP(B140, ABZ!A:A, ABZ!B:B, "", 0)) -> Sales Marketing
A141: 20250114_Ankuendigung_AVM_Mesh Set 4200_Edition_INT_DE_Final.docx | B141: Apa | C141: EN | D141: Joe | F141: Z:\Produkte\Texte Web, Marketing, etc\deutsch\2025.01 | G141: 45677 | H141: 45678 | I141: 45684 | J141: =IF(_xlfn.XLOOKUP(B141, ABZ!A:A, ABZ!B:B, "", 0) = 0, "", _xlfn.XLOOKUP(B141, ABZ!A:A, ABZ!B:B, "", 0)) -> Sales Marketing
A142: 20250114_Ankuendigung_AVM_Mesh Set 4200_Edition_INT_DE_Final.docx | B142: Apa | C142: FR | D142: Marie/Martine | F142: Z:\Produkte\Texte Web, Marketing, etc\deutsch\2025.01 | G142: 45677 | H142: 45678 | I142: 45684 | J142: =IF(_xlfn.XLOOKUP(B142, ABZ!A:A, ABZ!B:B, "", 0) = 0, "", _xlfn.XLOOKUP(B142, ABZ!A:A, ABZ!B:B, "", 0)) -> Sales Marketing
A143: 20250114_Ankuendigung_AVM_Mesh Set 4200_Edition_INT_DE_Final.docx | B143: Apa | C143: IT | D143: Cristina/Laura | F143: Z:\Produkte\Texte Web, Marketing, etc\deutsch\2025.01 | G143: 45677 | H143: 45686 | I143: 45684 | J143: =IF(_xlfn.XLOOKUP(B143, ABZ!A:A, ABZ!B:B, "", 0) = 0, "", _xlfn.XLOOKUP(B143, ABZ!A:A, ABZ!B:B, "", 0)) -> Sales Marketing
A144: 20250114_Ankuendigung_AVM_Mesh Set 4200_Edition_INT_DE_Final.docx | B144: Apa | C144: NL | D144: Angelique | F144: Z:\Produkte\Texte Web, Marketing, etc\deutsch\2025.01 | G144: 45677 | H144: 45800 | I144: 45684 | J144: =IF(_xlfn.XLOOKUP(B144, ABZ!A:A, ABZ!B:B, "", 0) = 0, "", _xlfn.XLOOKUP(B144, ABZ!A:A, ABZ!B:B, "", 0)) -> Sales Marketing
A145: 20250114_Ankuendigung_AVM_Mesh Set 4200_Edition_INT_DE_Final.docx | B145: Apa | C145: ES | D145: Marta/Helena | F145: Z:\Produkte\Texte Web, Marketing, etc\deutsch\2025.01 | G145: 45677 | H145: 45685 | I145: 45684 | J145: =IF(_xlfn.XLOOKUP(B145, ABZ!A:A, ABZ!B:B, "", 0) = 0, "", _xlfn.XLOOKUP(B145, ABZ!A:A, ABZ!B:B, "", 0)) -> Sales Marketing
A146: 20250114_Ankuendigung_AVM_Mesh Set 4200_Edition_INT_DE_Final.docx | B146: Apa | C146: PL | D146: Yabylon | F146: Z:\Produkte\Texte Web, Marketing, etc\deutsch\2025.01 | G146: 45677 | H146: 45681 | I146: 45684 | J146: =IF(_xlfn.XLOOKUP(B146, ABZ!A:A, ABZ!B:B, "", 0) = 0, "", _xlfn.XLOOKUP(B146, ABZ!A:A, ABZ!B:B, "", 0)) -> Sales Marketing
A147: MyFApp_20250120-de-FR.xliff | B147: KNu | C147: Fr | D147: Martine | E147: 137614 | F147: Z:\Produkte\F!Apps\FappMyF\GUI\iOS\franzoesisch\2025.01 | G147: 45677 | H147: 45679 | I147: 45680 | J147: =IF(_xlfn.XLOOKUP(B147, ABZ!A:A, ABZ!B:B, "", 0) = 0, "", _xlfn.XLOOKUP(B147, ABZ!A:A, ABZ!B:B, "", 0)) -> User Interface & Clients
A148: MyFApp_20250120-de-NL.xliff | B148: KNu | C148: Nl | D148: Angelique | E148: 137614 | F148: Z:\Produkte\F!Apps\FappMyF\GUI\iOS\niederlaendisch\2025.01 | G148: 45677 | H148: 45679 | I148: 45680 | J148: =IF(_xlfn.XLOOKUP(B148, ABZ!A:A, ABZ!B:B, "", 0) = 0, "", _xlfn.XLOOKUP(B148, ABZ!A:A, ABZ!B:B, "", 0)) -> User Interface & Clients
A149: MyFApp_20250120-de-ES.xliff | B149: KNu | C149: Es | D149: Helena | E149: 137614 | F149: Z:\Produkte\F!Apps\FappMyF\GUI\iOS\spanisch\2025.01 | G149: 45677 | H149: 45679 | I149: 45680 | J149: =IF(_xlfn.XLOOKUP(B149, ABZ!A:A, ABZ!B:B, "", 0) = 0, "", _xlfn.XLOOKUP(B149, ABZ!A:A, ABZ!B:B, "", 0)) -> User Interface & Clients
A150: MyFApp_20250120-de-IT.xliff | B150: KNu | C150: It | D150: Laura | E150: 137614 | F150: Z:\Produkte\F!Apps\FappMyF\GUI\iOS\italienisch\2025.01 | G150: 45677 | H150: 45679 | I150: 45680 | J150: =IF(_xlfn.XLOOKUP(B150, ABZ!A:A, ABZ!B:B, "", 0) = 0, "", _xlfn.XLOOKUP(B150, ABZ!A:A, ABZ!B:B, "", 0)) -> User Interface & Clients
A151: MyFApp_20250120-de-PL.xliff | B151: KNu | C151: Pl | D151: Yabylon | E151: 137614 | F151: Z:\Produkte\F!Apps\FappMyF\GUI\iOS\polnisch\2025.01 | G151: 45677 | H151: 45681 | I151: 45680 | J151: =IF(_xlfn.XLOOKUP(B151, ABZ!A:A, ABZ!B:B, "", 0) = 0, "", _xlfn.XLOOKUP(B151, ABZ!A:A, ABZ!B:B, "", 0)) -> User Interface & Clients
A152: MyFApp_20250120-de-US.xliff | B152: KNu | C152: En | D152: Joe | E152: 137614 | F152: Z:\Produkte\F!Apps\FappMyF\GUI\iOS\englisch\2025.01 | G152: 45677 | H152: 45313 | I152: 45680 | J152: =IF(_xlfn.XLOOKUP(B152, ABZ!A:A, ABZ!B:B, "", 0) = 0, "", _xlfn.XLOOKUP(B152, ABZ!A:A, ABZ!B:B, "", 0)) -> User Interface & Clients
A153: Vertriebs-kick-off_2-de-en.docx | B153: AGi | C153: De | D153: Franziska | E153: Mail | F153: Z:\Produkte\Texte Web, Marketing, etc\deutsch\2025.01 | G153: 45677 | H153: 45677 | I153: 45677 | J153: =IF(_xlfn.XLOOKUP(B153, ABZ!A:A, ABZ!B:B, "", 0) = 0, "", _xlfn.XLOOKUP(B153, ABZ!A:A, ABZ!B:B, "", 0)) -> Channel Sales
A154: Vertriebs-kick-off_2-de-en.docx | B154: AGi | C154: En | D154: Lisa | E154: Mail | F154: Z:\Produkte\Texte Web, Marketing, etc\deutsch\2025.01 | G154: 45677 | H154: 45684 | I154: 45684 | J154: =IF(_xlfn.XLOOKUP(B154, ABZ!A:A, ABZ!B:B, "", 0) = 0, "", _xlfn.XLOOKUP(B154, ABZ!A:A, ABZ!B:B, "", 0)) -> Channel Sales
A155: Die Barrierefreiheit von IT-Produkten-de.docx | B155: LLE | C155: EN | D155: Joe | E155: Mail | F155: Z:\Produkte\Texte Web, Marketing, etc\deutsch\2025.01 | G155: 45677 | H155: 45678 | I155: 45680 | J155: =IF(_xlfn.XLOOKUP(B155, ABZ!A:A, ABZ!B:B, "", 0) = 0, "", _xlfn.XLOOKUP(B155, ABZ!A:A, ABZ!B:B, "", 0)) -> Technical Communication
A156: FRITZ!Repeater 1200 AX_ITA-de-it.docx | B156: EUL | C156: IT | D156: Laura | E156: Mail | F156: Z:\Produkte\Texte Web, Marketing, etc\deutsch\2025.01 | G156: 45677 | H156: 45678 | I156: 45678 | J156: =IF(_xlfn.XLOOKUP(B156, ABZ!A:A, ABZ!B:B, "", 0) = 0, "", _xlfn.XLOOKUP(B156, ABZ!A:A, ABZ!B:B, "", 0)) -> Corporate Communications
A157: Vertriebs-kick-off_2-de-en.docx | B157: BAl | C157: EN | D157: Joe | E157: Mail | F157: Z:\Produkte\Texte Web, Marketing, etc\deutsch\2025.01 | G157: 45678 | H157: 45684 | I157: 45688 | J157: =IF(_xlfn.XLOOKUP(B157, ABZ!A:A, ABZ!B:B, "", 0) = 0, "", _xlfn.XLOOKUP(B157, ABZ!A:A, ABZ!B:B, "", 0)) -> Corporate Communications
A158: Einladung_MWC_2025_v2_de.docx | B158: BAl | C158: DE | D158: Franziska | E158: Mail | F158: Z:\Produkte\Texte Web, Marketing, etc\deutsch\2025.01 | G158: 45678 | H158: 45312 | I158: 45678 | J158: =IF(_xlfn.XLOOKUP(B158, ABZ!A:A, ABZ!B:B, "", 0) = 0, "", _xlfn.XLOOKUP(B158, ABZ!A:A, ABZ!B:B, "", 0)) -> Corporate Communications
A159: Einladung_MWC_2025_v2_de.docx | B159: BAl | C159: EN | D159: Joe | E159: Mail | F159: Z:\Produkte\Texte Web, Marketing, etc\deutsch\2025.01 | G159: 45678 | H159: 45313 | I159: 45679 | J159: =IF(_xlfn.XLOOKUP(B159, ABZ!A:A, ABZ!B:B, "", 0) = 0, "", _xlfn.XLOOKUP(B159, ABZ!A:A, ABZ!B:B, "", 0)) -> Corporate Communications
A160: WhatsApp-ES.docx | B160: JWg | C160: ES | D160: Helena | E160: Mail | F160: Z:\Produkte\Texte Web, Marketing, etc\spanisch\2025.01 | G160: 45678 | H160: 45678 | I160: 45679 | J160: =IF(_xlfn.XLOOKUP(B160, ABZ!A:A, ABZ!B:B, "", 0) = 0, "", _xlfn.XLOOKUP(B160, ABZ!A:A, ABZ!B:B, "", 0)) -> Channel Sales
A161: Händler Newsflash DE 02/2025 | B161: AGi | C161: De | D161: Franziska | E161: Mail | G161: 45677 | H161: 45678 | I161: 45678 | J161: =IF(_xlfn.XLOOKUP(B161, ABZ!A:A, ABZ!B:B, "", 0) = 0, "", _xlfn.XLOOKUP(B161, ABZ!A:A, ABZ!B:B, "", 0)) -> Channel Sales
A162: 20250121_PA_4690_DRAFT.docx | B162: PWi | C162: De | D162: Franziska | E162: Mail | G162: 45677 | H162: 45679 | I162: 45680 | J162: VTR-CS-CM-B2BPOS
A163: 220125_Script_FRITZ!Mesh-Set4200_Hutz_NG.docx | B163: Ngo | C163: EN | D163: Joe | E163: Mail | F163: Z:\Produkte\Texte Web, Marketing, etc\deutsch\2025.01 | G163: 45679 | H163: 45681 | I163: 45681 | J163: =IF(_xlfn.XLOOKUP(B163, ABZ!A:A, ABZ!B:B, "", 0) = 0, "", _xlfn.XLOOKUP(B163, ABZ!A:A, ABZ!B:B, "", 0)) -> Corporate Communications
A164: 220125_Script_FRITZ!Mesh-Set4200_Hutz_NG.docx | B164: Ngo | C164: NL | D164: Marion/Angelique | E164: Mail | F164: Z:\Produkte\Texte Web, Marketing, etc\deutsch\2025.01 | G164: 45679 | H164: 45679 | I164: 45681 | J164: =IF(_xlfn.XLOOKUP(B164, ABZ!A:A, ABZ!B:B, "", 0) = 0, "", _xlfn.XLOOKUP(B164, ABZ!A:A, ABZ!B:B, "", 0)) -> Corporate Communications
A165: 220125_Script_FRITZ!Mesh-Set4200_Hutz_NG.docx | B165: Ngo | C165: IT | D165: Cristina | E165: Mail | F165: Z:\Produkte\Texte Web, Marketing, etc\deutsch\2025.01 | G165: 45679 | H165: 45679 | I165: 45681 | J165: =IF(_xlfn.XLOOKUP(B165, ABZ!A:A, ABZ!B:B, "", 0) = 0, "", _xlfn.XLOOKUP(B165, ABZ!A:A, ABZ!B:B, "", 0)) -> Corporate Communications
A166: 220125_Script_FRITZ!Mesh-Set4200_Hutz_NG.docx | B166: Ngo | C166: ES | D166: Marta | E166: Mail | F166: Z:\Produkte\Texte Web, Marketing, etc\deutsch\2025.01 | G166: 45679 | H166: 45681 | I166: 45681 | J166: =IF(_xlfn.XLOOKUP(B166, ABZ!A:A, ABZ!B:B, "", 0) = 0, "", _xlfn.XLOOKUP(B166, ABZ!A:A, ABZ!B:B, "", 0)) -> Corporate Communications
A167: 220125_Script_FRITZ!Mesh-Set4200_Hutz_NG.docx | B167: Ngo | C167: FR | D167: Marie | E167: Mail | F167: Z:\Produkte\Texte Web, Marketing, etc\deutsch\2025.01 | G167: 45679 | H167: 45680 | I167: 45681 | J167: =IF(_xlfn.XLOOKUP(B167, ABZ!A:A, ABZ!B:B, "", 0) = 0, "", _xlfn.XLOOKUP(B167, ABZ!A:A, ABZ!B:B, "", 0)) -> Corporate Communications
A168: Das Genie hinter FRITZ-de.docx | B168: Bal | C168: EN | D168: Joe | E168: Mail | F168: Z:\Produkte\Texte Web, Marketing, etc\deutsch\2025.01 | G168: 45678 | H168: 45685 | I168: 45688 | J168: =IF(_xlfn.XLOOKUP(B168, ABZ!A:A, ABZ!B:B, "", 0) = 0, "", _xlfn.XLOOKUP(B168, ABZ!A:A, ABZ!B:B, "", 0)) -> Corporate Communications
A169: KA 6850 4G fehlende_texte_DE.docx | B169: OSt | C169: Pl | D169: Yabylon | E169: Mail | F169: Z:\Produkte\F!Box Kurzanleitungen\international\FRITZ!Box 6850 4G\2025.01 | G169: 45679 | H169: 45680 | I169: 45680 | J169: =IF(_xlfn.XLOOKUP(B169, ABZ!A:A, ABZ!B:B, "", 0) = 0, "", _xlfn.XLOOKUP(B169, ABZ!A:A, ABZ!B:B, "", 0)) -> Technical Communication
A170: 6820 LTE-de-it.docx | B170: EUL | C170: IT | D170: Laura | E170: Mail | F170: Z:\Produkte\Texte Web, Marketing, etc\italienisch\2025.01 | G170: 45679 | H170: 45688 | I170: 45686 | J170: =IF(_xlfn.XLOOKUP(B170, ABZ!A:A, ABZ!B:B, "", 0) = 0, "", _xlfn.XLOOKUP(B170, ABZ!A:A, ABZ!B:B, "", 0)) -> Corporate Communications
A171: 94137_en-GB_fritzmesh_wi_fi_set_4200_2er_20250123-112836.xml | B171: CST | C171: EN | D171: Joe | E171: Mail | F171: K:\Online\Online-Redaktion\2025\avm.de\Produkte\Mesh Wi-Fi Set 4200\Mesh Wi-Fi Set 4200 (2er)\Export | G171: 45680 | H171: 45684 | I171: 45684 | J171: =IF(_xlfn.XLOOKUP(B171, ABZ!A:A, ABZ!B:B, "", 0) = 0, "", _xlfn.XLOOKUP(B171, ABZ!A:A, ABZ!B:B, "", 0)) -> D2C Ecommerce
...

Sheet 2024
A1: Aufträge | B1: Vom | C1: Sprache | D1: Korrektur | E1: Jazz | F1: Ablageort | G1: Datum | H1: Lieferung | I1: Deadline | J1: Abteilung | K1: Ist… | L1: Abteilung
A2: Newsletter-Dezember_de-ES.docx | B2: JWg | C2: ES | D2: Helena | E2: Mail | F2: Z:\Produkte\Texte Web, Marketing, etc\deutsch\2023.12 | G2: 45279 | H2: 45299 | I2: 45299 | J2: =_xlfn.XLOOKUP(B2, ABZ!A:A, ABZ!B:B, "", 0) -> Channel Sales | L2: {=_xlfn.XLOOKUP(B2:B3003, ABZ!A:A, ABZ!B:B, "", 0)} -> Channel Sales
A3: 7 Vorteile: FRITZ!Powerline 1240 AX mit Wi-Fi 6 und Gigabit über die Stromleitung | B3: JBy | C3: EN | D3: Joe | G3: 45301 | H3: 45322 | J3: =_xlfn.XLOOKUP(B3, ABZ!A:A, ABZ!B:B, "", 0)
A4: Produktseite: Mesh Set 4060 + 3000 AX Product Features | B4: JBy | C4: EN | D4: Joe | H4: 45322 | J4: =_xlfn.XLOOKUP(B4, ABZ!A:A, ABZ!B:B, "", 0)
A5: Produktseite: Mesh Set 4060 + 3000 AX Product Features | B5: JBy | C5: FR | D5: Martine | H5: 45322 | J5: =_xlfn.XLOOKUP(B5, ABZ!A:A, ABZ!B:B, "", 0)
A6: Produktseite: Mesh Set 4060 + 3000 AX Product Features | B6: JBy | C6: NL | D6: Marion/Angelique | H6: 45322 | J6: =_xlfn.XLOOKUP(B6, ABZ!A:A, ABZ!B:B, "", 0)
A7: Produktseite: Mesh Set 4060 + 3000 AX Product Features | B7: JBy | C7: ES | D7: Marta/Helena | H7: 45322 | J7: =_xlfn.XLOOKUP(B7, ABZ!A:A, ABZ!B:B, "", 0)
A8: Produktseite: Mesh Set 4060 + 3000 AX Product Features | B8: JBy | C8: IT | D8: Cristina/Laura | H8: 45322 | J8: =_xlfn.XLOOKUP(B8, ABZ!A:A, ABZ!B:B, "", 0)
A9: Produktseite: Mesh Set 4060 + 3000 AX Product Features | B9: JBy | C9: PL | D9: Yabylon | H9: 45322 | J9: =_xlfn.XLOOKUP(B9, ABZ!A:A, ABZ!B:B, "", 0)
A10: Produktseite: Mesh Set 7530 AX + 1200 Ed. Int. (20003051) | B10: JBy | C10: EN | D10: Joe | H10: 45322 | J10: =_xlfn.XLOOKUP(B10, ABZ!A:A, ABZ!B:B, "", 0)
A11: FRITZ!DECT 350 – Der Tür- und Fensterkontakt für smarte Möglichkeiten | B11: JBy | C11: EN | H11: 45322 | J11: =_xlfn.XLOOKUP(B11, ABZ!A:A, ABZ!B:B, "", 0)
A12: Sicheres Surfen im Internet | B12: JBy | C12: EN | H12: 45322 | J12: =_xlfn.XLOOKUP(B12, ABZ!A:A, ABZ!B:B, "", 0)
A13: Sicheres Surfen im Internet | B13: JBy | C13: FR | H13: 45322 | J13: =_xlfn.XLOOKUP(B13, ABZ!A:A, ABZ!B:B, "", 0)
A14: Sicheres Surfen im Internet | B14: JBy | C14: NL | H14: 45322 | J14: =_xlfn.XLOOKUP(B14, ABZ!A:A, ABZ!B:B, "", 0)
A15: Sicheres Surfen im Internet | B15: JBy | C15: ES | H15: 45322 | J15: =_xlfn.XLOOKUP(B15, ABZ!A:A, ABZ!B:B, "", 0)
A16: Sicheres Surfen im Internet | B16: JBy | C16: IT | H16: 45322 | J16: =_xlfn.XLOOKUP(B16, ABZ!A:A, ABZ!B:B, "", 0)
A17: Sicheres Surfen im Internet | B17: JBy | C17: PL | H17: 45322 | J17: =_xlfn.XLOOKUP(B17, ABZ!A:A, ABZ!B:B, "", 0)
A18: Alles über sichere Passwörter | B18: JBy | C18: EN | H18: 45322 | J18: =_xlfn.XLOOKUP(B18, ABZ!A:A, ABZ!B:B, "", 0)
A19: Alles über sichere Passwörter | B19: JBy | C19: FR | H19: 45322 | J19: =_xlfn.XLOOKUP(B19, ABZ!A:A, ABZ!B:B, "", 0)
A20: Alles über sichere Passwörter | B20: JBy | C20: NL | H20: 45322 | J20: =_xlfn.XLOOKUP(B20, ABZ!A:A, ABZ!B:B, "", 0)
A21: Alles über sichere Passwörter | B21: JBy | C21: ES | H21: 45322 | J21: =_xlfn.XLOOKUP(B21, ABZ!A:A, ABZ!B:B, "", 0)
A22: Alles über sichere Passwörter | B22: JBy | C22: IT | H22: 45322 | J22: =_xlfn.XLOOKUP(B22, ABZ!A:A, ABZ!B:B, "", 0)
... A78: Ändern oder lieber nicht? So erhöhen Sie die Sicherheit Ihrer Passwörter | B78: JBy | C78: NL | H78: 45322 | J78: =_xlfn.XLOOKUP(B78, ABZ!A:A, ABZ!B:B, "", 0)
A79: PI_AVM_RC_Glasfaser_Update_FRITZ!OS_7-80_1-de.docx | B79: CSa | C79: En | D79: Susan | E79: Mail | F79: Z:\Produkte\Texte Web, Marketing, etc\deutsch\2023.12 | G79: 45280 | H79: 45280 | I79: 45281 | J79: =_xlfn.XLOOKUP(B79, ABZ!A:A, ABZ!B:B, "", 0)
A80: Master_Move21_Version_30_2024-01-04_D-00000020_T-00000571_EngineeringModules_de-DE_es-ES.xml | B80: CMi | C80: ES | D80: Helena | F80: Z:\International\Tico\work\2024-01-04_D-00000020_T-00000571_de-DE_es-ES.xml | G80: 45295 | H80: 45299 | J80: =_xlfn.XLOOKUP(B80, ABZ!A:A, ABZ!B:B, "", 0) -> Technical Communication | L80: Technical Communication
A81: Master_Move21_Version_30_2024-01-04_D-00000020_T-00000570_EngineeringModules_de-DE_fr-FR.xml | B81: CMi | C81: FR | D81: Martine | F81: Z:\International\Tico\work\2024-01-04_D-00000020_T-00000570_de-DE_fr-FR.xml | G81: 45295 | H81: 45303 | J81: =_xlfn.XLOOKUP(B81, ABZ!A:A, ABZ!B:B, "", 0) -> Technical Communication | L81: Technical Communication
A82: Master_Move21_Version_30_2024-01-04_D-00000020_T-00000569_EngineeringModules_de-DE_en-US.xml | B82: CMi | C82: EN | D82: Susan | F82: Z:\International\Tico\work\2024-01-04_D-00000020_T-00000569_de-DE_en-US.xml | G82: 45295 | H82: 45299 | J82: =_xlfn.XLOOKUP(B82, ABZ!A:A, ABZ!B:B, "", 0) -> Technical Communication | L82: Technical Communication
A83: Master_Move21_Version_30_2024-01-04_D-00000020_T-00000572_EngineeringModules_de-DE_it-IT.xml | B83: CMi | C83: IT | D83: Laura | F83: Z:\International\Tico\work\2024-01-04_D-00000020_T-00000572_de-DE_it-IT.xml | G83: 45295 | H83: 45330 | J83: =_xlfn.XLOOKUP(B83, ABZ!A:A, ABZ!B:B, "", 0) -> Technical Communication | L83: Technical Communication
A84: Master_Move21_Version_30_2024-01-04_D-00000020_T-00000573_EngineeringModules_de-DE_nl-NL.xml | B84: CMi | C84: NL | D84: angelique | F84: Z:\International\Tico\work\2024-01-04_D-00000020_T-00000573_de-DE_nl-NL.xml | G84: 45295 | H84: 45303 | J84: =_xlfn.XLOOKUP(B84, ABZ!A:A, ABZ!B:B, "", 0) -> Technical Communication | L84: Technical Communication
A85: js3-i18n--2024-01-05.html | B85: SLm | C85: EN | D85: Susan | F85: \\file-fs-04.ads.avm.de\AVM\Anwendung\FileSplit | G85: 45299 | H85: 45299 | J85: =_xlfn.XLOOKUP(B85, ABZ!A:A, ABZ!B:B, "", 0) -> User Interface & Clients | L85: User Interface & Clients
A86: js3-i18n--2024-01-05.html | B86: SLm | C86: FR | D86: Martine | F86: \\file-fs-04.ads.avm.de\AVM\Anwendung\FileSplit | G86: 45299 | H86: 45299 | J86: =_xlfn.XLOOKUP(B86, ABZ!A:A, ABZ!B:B, "", 0) -> User Interface & Clients | L86: User Interface & Clients
A87: js3-i18n--2024-01-05.html | B87: SLm | C87: IT | D87: Laura | F87: \\file-fs-04.ads.avm.de\AVM\Anwendung\FileSplit | G87: 45299 | H87: 45299 | J87: =_xlfn.XLOOKUP(B87, ABZ!A:A, ABZ!B:B, "", 0) -> User Interface & Clients | L87: User Interface & Clients
A88: js3-i18n--2024-01-05.html | B88: SLm | C88: NL | D88: Angelique | F88: \\file-fs-04.ads.avm.de\AVM\Anwendung\FileSplit | G88: 45299 | H88: 45299 | J88: =_xlfn.XLOOKUP(B88, ABZ!A:A, ABZ!B:B, "", 0) -> User Interface & Clients | L88: User Interface & Clients
A89: js3-i18n--2024-01-05.html | B89: SLm | C89: ES | D89: Helena | F89: \\file-fs-04.ads.avm.de\AVM\Anwendung\FileSplit | G89: 45299 | H89: 45299 | J89: =_xlfn.XLOOKUP(B89, ABZ!A:A, ABZ!B:B, "", 0) -> User Interface & Clients | L89: User Interface & Clients
A90: js3-i18n--2024-01-05.html | B90: SLm | C90: PL | D90: Yabylon | F90: \\file-fs-04.ads.avm.de\AVM\Anwendung\FileSplit | G90: 45299 | H90: 45299 | J90: =_xlfn.XLOOKUP(B90, ABZ!A:A, ABZ!B:B, "", 0) -> User Interface & Clients | L90: User Interface & Clients
A91: 7690_Produktspezifikation_ 2023-11-de.docx | B91: AZi | C91: En | D91: Susan | E91: Mail | F91: Z:\Produkte\F!Box 7690\ExecSum\deutsch | G91: 45299 | H91: 45299 | I91: 45303 | J91: =_xlfn.XLOOKUP(B91, ABZ!A:A, ABZ!B:B, "", 0) -> Product Management | L91: Product Management
A92: Newsletter-IT-Jan.docx | B92: JWg | C92: IT | D92: Cristina/Laura | E92: Mail | F92: Z:\Produkte\Texte Web, Marketing, etc\italienisch\2024.01 | G92: 45301 | H92: 45302 | J92: =_xlfn.XLOOKUP(B92, ABZ!A:A, ABZ!B:B, "", 0) -> Channel Sales | L92: Channel Sales
A93: Business_Update_Januar-DE.docx | B93: SDa | C93: NL | D93: Angelique | E93: Mail | F93: Z:\Produkte\Texte Web, Marketing, etc\deutsch\2024.01 | G93: 45302 | H93: 45306 | I93: 45308 | J93: =_xlfn.XLOOKUP(B93, ABZ!A:A, ABZ!B:B, "", 0) -> Channel Sales | L93: Channel Sales
A94: Hintergrundstext zur Routerfreiheit (deutsch).docx | B94: JBy | C94: IT | D94: Cristina/Laura | E94: Mail | F94: Z:\Produkte\Texte Web, Marketing, etc\deutsch\2024.01 | G94: 45302 | H94: 45320 | J94: =_xlfn.XLOOKUP(B94, ABZ!A:A, ABZ!B:B, "", 0)
A95: Hintergrundstext zur Routerfreiheit (deutsch).docx | B95: JBy | C95: FR | D95: Martine | E95: Mail | F95: Z:\Produkte\Texte Web, Marketing, etc\deutsch\2024.01 | G95: 45302 | H95: 45310 | J95: =_xlfn.XLOOKUP(B95, ABZ!A:A, ABZ!B:B, "", 0)
A96: FAppMyFRITZ_20240115-de-US.xliff | B96: RWr | C96: En | D96: Susan | E96: 122589 | F96: Z:\Produkte\F!Apps\FappMyF\GUI\iOS\englisch\2024.01 | G96: 45306 | H96: 45310 | J96: =_xlfn.XLOOKUP(B96, ABZ!A:A, ABZ!B:B, "", 0) -> User Interface & Clients | L96: User Interface & Clients
A97: FAppMyFRITZ_20240115-de-ES.xliff | B97: RWr | C97: ES | D97: Helena | E97: 122589 | F97: Z:\Produkte\F!Apps\FappMyF\GUI\iOS\spanisch\2024.01 | G97: 45306 | H97: 44949 | J97: =_xlfn.XLOOKUP(B97, ABZ!A:A, ABZ!B:B, "", 0) -> User Interface & Clients | L97: User Interface & Clients
A98: FAppMyFRITZ_20240115-de-FR.xliff | B98: RWr | C98: Fr | D98: Martine | E98: 122589 | F98: Z:\Produkte\F!Apps\FappMyF\GUI\iOS\franzoesisch\2024.01 | G98: 45306 | H98: 45321 | J98: =_xlfn.XLOOKUP(B98, ABZ!A:A, ABZ!B:B, "", 0) -> User Interface & Clients | L98: User Interface & Clients
A99: FAppMyFRITZ_20240115-de-IT.xliff | B99: RWr | C99: It | D99: Laura | E99: 122589 | F99: Z:\Produkte\F!Apps\FappMyF\GUI\iOS\italienisch\2024.01 | G99: 45306 | H99: 45310 | J99: =_xlfn.XLOOKUP(B99, ABZ!A:A, ABZ!B:B, "", 0) -> User Interface & Clients | L99: User Interface & Clients
A100: FAppMyFRITZ_20240115-de-NL.xliff | B100: RWr | C100: Nl | D100: Angelique | E100: 122589 | F100: Z:\Produkte\F!Apps\FappMyF\GUI\iOS\niederlaendisch\2024.01 | G100: 45306 | H100: 45310 | J100: =_xlfn.XLOOKUP(B100, ABZ!A:A, ABZ!B:B, "", 0) -> User Interface & Clients | L100: User Interface & Clients
A101: FAppMyFRITZ_20240115-de-PL.xliff | B101: RWr | C101: Pl | D101: Yabylon | E101: 122589 | F101: Z:\Produkte\F!Apps\FappMyF\GUI\iOS\polnisch\2024.01 | G101: 45306 | H101: 45315 | I101: 45315 | J101: =_xlfn.XLOOKUP(B101, ABZ!A:A, ABZ!B:B, "", 0) -> User Interface & Clients | L101: User Interface & Clients
A102: 0000_12.998.1.51.2.10.2.13_translate-from-de | B102: GAb | C102: EN | D102: Susan | F102: Z:\Produkte\F!Box allgemein\GUI-alt\deutsch\2024.01 | G102: 45310 | H102: 45315 | J102: =_xlfn.XLOOKUP(B102, ABZ!A:A, ABZ!B:B, "", 0) -> User Interface & Clients | L102: User Interface & Clients
A103: 0000_12.998.1.51.2.10.2.13_translate-from-de | B103: GAb | C103: IT | D103: Laura | F103: Z:\Produkte\F!Box allgemein\GUI-alt\italienisch\2024.01 | G103: 45310 | H103: 45315 | J103: =_xlfn.XLOOKUP(B103, ABZ!A:A, ABZ!B:B, "", 0) -> User Interface & Clients | L103: User Interface & Clients
A104: 0000_12.998.1.51.2.10.2.13_translate-from-de | B104: GAb | C104: FR | D104: Martine | F104: Z:\Produkte\F!Box allgemein\GUI-alt\deutsch\2024.01 | G104: 45310 | H104: 45315 | J104: =_xlfn.XLOOKUP(B104, ABZ!A:A, ABZ!B:B, "", 0) -> User Interface & Clients | L104: User Interface & Clients
A105: 0000_12.998.1.51.2.10.2.13_translate-from-de | B105: GAb | C105: NL | D105: Angelique | F105: Z:\Produkte\F!Box allgemein\GUI-alt\deutsch\2024.01 | G105: 45310 | H105: 45315 | J105: =_xlfn.XLOOKUP(B105, ABZ!A:A, ABZ!B:B, "", 0) -> User Interface & Clients | L105: User Interface & Clients
A106: 0000_12.998.1.51.2.10.2.13_translate-from-de | B106: GAb | C106: ES | D106: Helena | F106: Z:\Produkte\F!Box allgemein\GUI-alt\deutsch\2024.01 | G106: 45310 | H106: 45315 | J106: =_xlfn.XLOOKUP(B106, ABZ!A:A, ABZ!B:B, "", 0) -> User Interface & Clients | L106: User Interface & Clients
A107: 12.998.1.51.2.10.2.13_translate-from-de-to-pl | B107: GAb | C107: PL | D107: Yabylon | F107: Z:\Produkte\F!Box allgemein\GUI-alt\deutsch\2024.01 | G107: 45310 | H107: 45315 | J107: =_xlfn.XLOOKUP(B107, ABZ!A:A, ABZ!B:B, "", 0) -> User Interface & Clients | L107: User Interface & Clients
A108: 1526_nl-NL_dienstverleners_20240122-135054.xml | B108: SDa | C108: NL | D108: Angelique | F108: Z:\Produkte\Texte Web, Marketing, etc\deutsch\2024.01 | G108: 45313 | H108: 45321 | I108: 45320 | J108: =_xlfn.XLOOKUP(B108, ABZ!A:A, ABZ!B:B, "", 0) -> Channel Sales | L108: Channel Sales
A109: 3159_nl-NL_digitaler_kundenservice_dank_fritzbox_und_co_20240122-135103.xml | B109: SDa | C109: NL | D109: Angelique | F109: Z:\Produkte\Texte Web, Marketing, etc\deutsch\2024.01 | G109: 45313 | H109: 45321 | I109: 45320 | J109: =_xlfn.XLOOKUP(B109, ABZ!A:A, ABZ!B:B, "", 0) -> Channel Sales | L109: Channel Sales
A110: Extension Labels Übersetzungen_de.xlsx | B110: JBy | C110: FR | D110: Martine | F110: Z:\Produkte\Texte Web, Marketing, etc\deutsch\2024.01 | G110: 45314 | H110: 45336 | I110: 45341 | J110: =_xlfn.XLOOKUP(B110, ABZ!A:A, ABZ!B:B, "", 0)
A111: Extension Labels Übersetzungen_de.xlsx | B111: JBy | C111: IT | D111: Cristina/Laura | F111: Z:\Produkte\Texte Web, Marketing, etc\deutsch\2024.01 | G111: 45314 | H111: 45338 | I111: 45341 | J111: =_xlfn.XLOOKUP(B111, ABZ!A:A, ABZ!B:B, "", 0)
A112: Extension Labels Übersetzungen_de.xlsx | B112: JBy | C112: NL | D112: Angelique | F112: Z:\Produkte\Texte Web, Marketing, etc\deutsch\2024.01 | G112: 45314 | H112: 45338 | I112: 45341 | J112: =_xlfn.XLOOKUP(B112, ABZ!A:A, ABZ!B:B, "", 0)
A113: Extension Labels Übersetzungen_de.xlsx | B113: JBy | C113: ES | D113: Helena | F113: Z:\Produkte\Texte Web, Marketing, etc\deutsch\2024.01 | G113: 45314 | H113: 45338 | I113: 45341 | J113: =_xlfn.XLOOKUP(B113, ABZ!A:A, ABZ!B:B, "", 0)
A114: Extension Labels Übersetzungen_de.xlsx | B114: JBy | C114: PL | D114: Yabylon | F114: Z:\Produkte\Texte Web, Marketing, etc\deutsch\2024.01 | G114: 45314 | H114: 44970 | I114: 45341 | J114: =_xlfn.XLOOKUP(B114, ABZ!A:A, ABZ!B:B, "", 0)
A115: fritzpowerline.en.xlf | B115: OBe | C115: En | D115: Susan | E115: Mail | F115: Z:\Produkte\F!Powerline\GUI\deutsch\2024.01 | G115: 45314 | H115: 45330 | I115: 45322 | J115: =_xlfn.XLOOKUP(B115, ABZ!A:A, ABZ!B:B, "", 0) -> Research & Development | L115: Research & Development
A116: Vertriebs-Kick-off-2024-de.docx | B116: ALe | C116: En | D116: Joe | E116: Mail | F116: Z:\Produkte\Texte Web, Marketing, etc\deutsch\2024.01 | G116: 45314 | H116: 45316 | I116: 45316 | J116: =_xlfn.XLOOKUP(B116, ABZ!A:A, ABZ!B:B, "", 0) -> Vertriebscontrolling | L116: Vertriebscontrolling
A117: Schon_gewusst_Teaser-de.docx | B117: JWg | C117: It | D117: Cristina/Laura | E117: Mail | F117: Z:\Produkte\Texte Web, Marketing, etc\italienisch\2024.01 | G117: 45315 | H117: 45320 | I117: 45322 | J117: =_xlfn.XLOOKUP(B117, ABZ!A:A, ABZ!B:B, "", 0) -> Channel Sales | L117: Channel Sales
A118: Schon_gewusst_Teaser-de.docx | B118: JWg | C118: Nl | D118: Angelique | E118: Mail | F118: Z:\Produkte\Texte Web, Marketing, etc\deutsch\2024.01 | G118: 45315 | H118: 45320 | I118: 45322 | J118: =_xlfn.XLOOKUP(B118, ABZ!A:A, ABZ!B:B, "", 0) -> Channel Sales | L118: Channel Sales
A119: FappSH_20240124-de-ES.xliff | B119: CWy | C119: ES | D119: Helena | E119: 123225 | F119: Z:\Produkte\F!Apps\FappSmartHome\GUI\iOS\spanisch\2024.01 | G119: 45315 | H119: 45320 | I119: 45320 | J119: =_xlfn.XLOOKUP(B119, ABZ!A:A, ABZ!B:B, "", 0) -> User Interface & Clients | L119: User Interface & Clients
A120: FappSH_20240124-de-FR.xliff | B120: CWy | C120: Fr | D120: Martine | E120: 123225 | F120: Z:\Produkte\F!Apps\FappSmartHome\GUI\iOS\franzoesisch\2024.01 | G120: 45315 | H120: 45327 | I120: 45320 | J120: =_xlfn.XLOOKUP(B120, ABZ!A:A, ABZ!B:B, "", 0) -> User Interface & Clients | L120: User Interface & Clients
A121: FappSH_20240124-de-IT.xliff | B121: CWy | C121: It | D121: Laura | E121: 123225 | F121: Z:\Produkte\F!Apps\FappSmartHome\GUI\iOS\italienisch\2024.01 | G121: 45315 | H121: 45327 | I121: 45320 | J121: =_xlfn.XLOOKUP(B121, ABZ!A:A, ABZ!B:B, "", 0) -> User Interface & Clients | L121: User Interface & Clients
A122: FappSH_20240124-de-NL.xliff | B122: CWy | C122: Nl | D122: Angelique | E122: 123225 | F122: Z:\Produkte\F!Apps\FappSmartHome\GUI\iOS\niederlaendisch\2024.01 | G122: 45315 | H122: 45327 | I122: 45320 | J122: =_xlfn.XLOOKUP(B122, ABZ!A:A, ABZ!B:B, "", 0) -> User Interface & Clients | L122: User Interface & Clients
A123: FappSH_20240124-de-PL.xliff | B123: CWy | C123: Pl | D123: Yabylon | E123: 123225 | F123: Z:\Produkte\F!Apps\FappSmartHome\GUI\iOS\polnisch\2024.01 | G123: 45315 | H123: 45327 | I123: 45320 | J123: =_xlfn.XLOOKUP(B123, ABZ!A:A, ABZ!B:B, "", 0) -> User Interface & Clients | L123: User Interface & Clients
A124: FappSH_20240124-de-US.xliff | B124: CWy | C124: En | D124: Susan | E124: 123225 | F124: Z:\Produkte\F!Apps\FappSmartHome\GUI\iOS\englisch\2024.01 | G124: 45315 | H124: 45327 | I124: 45320 | J124: =_xlfn.XLOOKUP(B124, ABZ!A:A, ABZ!B:B, "", 0) -> User Interface & Clients | L124: User Interface & Clients
A125: GoFiber_Version_2_2024-01-24_D-00000069_T-00000574_EngineeringModules_de-DE_en-US.xml | B125: Doku | C125: EN | D125: Susan | F125: Z:\International\Tico\work\2024-01-24_D-00000069_T-00000574_de-DE_en-US.xml | G125: 45315 | H125: 45321 | J125: =_xlfn.XLOOKUP(B125, ABZ!A:A, ABZ!B:B, "", 0) -> Technical Communication | L125: Technical Communication
A126: GoFiber_Version_2_2024-01-24_D-00000069_T-00000577_EngineeringModules_de-DE_it-IT.xml | B126: Doku | C126: IT | D126: Laura | F126: Z:\International\Tico\work\2024-01-24_D-00000069_T-00000577_de-DE_it-IT.xml | G126: 45315 | H126: 45321 | J126: =_xlfn.XLOOKUP(B126, ABZ!A:A, ABZ!B:B, "", 0) -> Technical Communication | L126: Technical Communication
A127: GoFiber_Version_2_2024-01-24_D-00000069_T-00000578_EngineeringModules_de-DE_nl-NL.xml | B127: Doku | C127: NL | D127: Angelique | F127: Z:\International\Tico\work\2024-01-24_D-00000069_T-00000578_de-DE_nl-NL.xml\untranslated | G127: 45315 | H127: 45322 | J127: =_xlfn.XLOOKUP(B127, ABZ!A:A, ABZ!B:B, "", 0) -> Technical Communication | L127: Technical Communication
A128: GoFiber_Version_2_2024-01-24_D-00000069_T-00000575_EngineeringModules_de-DE_fr-FR.xml | B128: Doku | C128: FR | D128: Martine | F128: Z:\International\Tico\work\2024-01-24_D-00000069_T-00000575_de-DE_fr-FR.xml | G128: 45315 | H128: 45322 | J128: =_xlfn.XLOOKUP(B128, ABZ!A:A, ABZ!B:B, "", 0) -> Technical Communication | L128: Technical Communication
A129: GoFiber_Version_2_2024-01-24_D-00000069_T-00000576_EngineeringModules_de-DE_es-ES.xml | B129: Doku | C129: ES | D129: Helena | F129: Z:\International\Tico\work\2024-01-24_D-00000069_T-00000576_de-DE_es-ES.xml | G129: 45315 | H129: 45321 | J129: =_xlfn.XLOOKUP(B129, ABZ!A:A, ABZ!B:B, "", 0) -> Technical Communication | L129: Technical Communication
A130: Welcome_Business_Portal-de.docx | B130: SDa | C130: ES | D130: Marta/Helena | E130: Mail | F130: Z:\Produkte\Texte Web, Marketing, etc\deutsch\2024.01 | G130: 45315 | H130: 45321 | I130: 45323 | J130: =_xlfn.XLOOKUP(B130, ABZ!A:A, ABZ!B:B, "", 0) -> Channel Sales | L130: Channel Sales
A131: Welcome_Business_Portal-de.docx | B131: SDa | C131: It | D131: Cristina/Laura | E131: Mail | F131: Z:\Produkte\Texte Web, Marketing, etc\deutsch\2024.01 | G131: 45315 | H131: 45321 | I131: 45323 | J131: =_xlfn.XLOOKUP(B131, ABZ!A:A, ABZ!B:B, "", 0) -> Channel Sales | L131: Channel Sales
A132: Welcome_Business_Portal-de.docx | B132: SDa | C132: Nl | D132: Angelique | E132: Mail | F132: Z:\Produkte\Texte Web, Marketing, etc\deutsch\2024.01 | G132: 45315 | H132: 44955 | I132: 45323 | J132: =_xlfn.XLOOKUP(B132, ABZ!A:A, ABZ!B:B, "", 0) -> Channel Sales | L132: Channel Sales
A133: Handbuch_FB_Move21_v3-2024-01-24_D-00000058_T-00000579_EngineeringModules_de-DE_en-US | B133: VDi | C133: EN | D133: Susan | F133: Z:\International\Tico\work\2024-01-24_D-00000058_T-00000579_de-DE_en-US.xml | G133: 45315 | H133: 45322 | I133: 45327 | J133: =_xlfn.XLOOKUP(B133, ABZ!A:A, ABZ!B:B, "", 0) -> Technical Communication | L133: Technical Communication
A134: Handbuch_FB_Move21_v3-2024-01-24_D-00000058_T-00000582_EngineeringModules_de-DE_it-IT | B134: VDi | C134: IT | D134: Laura | F134: Z:\International\Tico\work\2024-01-24_D-00000058_T-00000582_de-DE_it-IT.xml | G134: 45315 | H134: 45324 | I134: 45327 | J134: =_xlfn.XLOOKUP(B134, ABZ!A:A, ABZ!B:B, "", 0) -> Technical Communication | L134: Technical Communication
A135: Handbuch_FB_Move21_v3-2024-01-24_D-00000058_T-00000583_EngineeringModules_de-DE_nl-NL | B135: VDi | C135: NL | D135: Angelique | F135: Z:\International\Tico\work\2024-01-24_D-00000058_T-00000583_de-DE_nl-NL.xml | G135: 45315 | H135: 45296 | I135: 45327 | J135: =_xlfn.XLOOKUP(B135, ABZ!A:A, ABZ!B:B, "", 0) -> Technical Communication | L135: Technical Communication
A136: Handbuch_FB_Move21_v3-2024-01-24_D-00000058_T-00000581_EngineeringModules_de-DE_es-ES | B136: VDi | C136: ES | D136: Helena | F136: Z:\International\Tico\work\2024-01-24_D-00000058_T-00000581_de-DE_es-ES.xml | G136: 45315 | H136: 45323 | I136: 45327 | J136: =_xlfn.XLOOKUP(B136, ABZ!A:A, ABZ!B:B, "", 0) -> Technical Communication | L136: Technical Communication
A137: Handbuch_FB_Move21_v3-2024-01-24_D-00000058_T-00000580_EngineeringModules_de-DE_fr-FR | B137: VDi | C137: FR | D137: Martine | F137: Z:\International\Tico\work\2024-01-24_D-00000058_T-00000580_de-DE_fr-FR.xml | G137: 45315 | H137: 45323 | I137: 45327 | J137: =_xlfn.XLOOKUP(B137, ABZ!A:A, ABZ!B:B, "", 0) -> Technical Communication | L137: Technical Communication
A138: Digitales-Zertifikat-de | B138: SDa | C138: NL | D138: Angelique | F138: Z:\Produkte\Texte Web, Marketing, etc\deutsch\2024.01 | G138: 45316 | H138: 45320 | I138: 45322 | J138: =_xlfn.XLOOKUP(B138, ABZ!A:A, ABZ!B:B, "", 0) -> Channel Sales | L138: Channel Sales
A139: Digitales-Zertifikat-de | B139: SDa | C139: IT | D139: Cristina/Laura | F139: Z:\Produkte\Texte Web, Marketing, etc\italienisch\2024.01 | G139: 45316 | H139: 45321 | I139: 45322 | J139: =_xlfn.XLOOKUP(B139, ABZ!A:A, ABZ!B:B, "", 0) -> Channel Sales | L139: Channel Sales
A140: Digitales-Zertifikat-de | B140: SDa | C140: ES | D140: Marta/Helena | F140: Z:\Produkte\Texte Web, Marketing, etc\deutsch\2024.01 | G140: 45316 | H140: 45320 | I140: 45322 | J140: =_xlfn.XLOOKUP(B140, ABZ!A:A, ABZ!B:B, "", 0) -> Channel Sales | L140: Channel Sales
A141: de.json => <Sprachkürzel>.json | B141: PNe | C141: En | D141: Susan | E141: 123485 | F141: Z:\Produkte\MyFRITZ\deutsch\2024.01\Webapp | G141: 45317 | H141: 45327 | I141: 45322 | J141: =_xlfn.XLOOKUP(B141, ABZ!A:A, ABZ!B:B, "", 0) -> IT | L141: IT
A142: de.json => <Sprachkürzel>.json | B142: PNe | C142: ES | D142: Helena | E142: 123485 | F142: Z:\Produkte\MyFRITZ\deutsch\2024.01\Webapp | G142: 45317 | H142: 45327 | I142: 45322 | J142: =_xlfn.XLOOKUP(B142, ABZ!A:A, ABZ!B:B, "", 0) -> IT | L142: IT
A143: de.json => <Sprachkürzel>.json | B143: PNe | C143: Fr | D143: Martine | E143: 123485 | F143: Z:\Produkte\MyFRITZ\franzoesisch\2024.01\Webapp | G143: 45317 | H143: 45327 | I143: 45322 | J143: =_xlfn.XLOOKUP(B143, ABZ!A:A, ABZ!B:B, "", 0) -> IT | L143: IT
A144: de.json => <Sprachkürzel>.json | B144: PNe | C144: It | D144: Laura | E144: 123485 | F144: Z:\Produkte\MyFRITZ\italienisch\2024.01\Webapp | G144: 45317 | H144: 45327 | I144: 45322 | J144: =_xlfn.XLOOKUP(B144, ABZ!A:A, ABZ!B:B, "", 0) -> IT | L144: IT
A145: de.json => <Sprachkürzel>.json | B145: PNe | C145: Nl | D145: Angelique | E145: 123485 | F145: Z:\Produkte\MyFRITZ\deutsch\2024.01\Webapp | G145: 45317 | H145: 45327 | I145: 45322 | J145: =_xlfn.XLOOKUP(B145, ABZ!A:A, ABZ!B:B, "", 0) -> IT | L145: IT
A146: FappMyF_20240129-de.xml | B146: JRn | C146: EN | D146: Susan | E146: 123595 | F146: Z:\Produkte\F!Apps\FappMyF\GUI\Android\deutsch\2024.01 | G146: 45320 | H146: 45322 | J146: =_xlfn.XLOOKUP(B146, ABZ!A:A, ABZ!B:B, "", 0) -> User Interface & Clients | L146: User Interface & Clients
A147: FappMyF_20240129-de.xml | B147: JRn | C147: FR | D147: Martine | E147: 123595 | G147: 45320 | H147: 45323 | J147: =_xlfn.XLOOKUP(B147, ABZ!A:A, ABZ!B:B, "", 0) -> User Interface & Clients | L147: User Interface & Clients
A148: FappMyF_20240129-de.xml | B148: JRn | C148: IT | D148: Laura | E148: 123595 | G148: 45320 | H148: 45322 | J148: =_xlfn.XLOOKUP(B148, ABZ!A:A, ABZ!B:B, "", 0) -> User Interface & Clients | L148: User Interface & Clients
A149: FappMyF_20240129-de.xml | B149: JRn | C149: NL | D149: Angelique | E149: 123595 | G149: 45320 | H149: 45322 | J149: =_xlfn.XLOOKUP(B149, ABZ!A:A, ABZ!B:B, "", 0) -> User Interface & Clients | L149: User Interface & Clients
A150: FappMyF_20240129-de.xml | B150: JRn | C150: ES | D150: Helena | E150: 123595 | G150: 45320 | H150: 45322 | J150: =_xlfn.XLOOKUP(B150, ABZ!A:A, ABZ!B:B, "", 0) -> User Interface & Clients | L150: User Interface & Clients
A151: FappMyF_20240129-de.xml | B151: JRn | C151: PL | D151: Yabylon | E151: 123595 | G151: 45320 | H151: 44959 | J151: =_xlfn.XLOOKUP(B151, ABZ!A:A, ABZ!B:B, "", 0) -> User Interface & Clients | L151: User Interface & Clients
A152: Fapp_adc_20240129-de.xml | B152: JRn | C152: EN | D152: Susan | E152: 123595 | F152: Z:\Produkte\F!Apps\Apps_allgemein\ADC\deutsch\2024.01 | G152: 45320 | H152: 45320 | J152: =_xlfn.XLOOKUP(B152, ABZ!A:A, ABZ!B:B, "", 0) -> User Interface & Clients | L152: User Interface & Clients
A153: Fapp_adc_20240129-de.xml | B153: JRn | C153: FR | D153: Martine | E153: 123595 | F153: Z:\Produkte\F!Apps\Apps_allgemein\ADC\franzoesisch\2024.01 | G153: 45320 | H153: 45321 | J153: =_xlfn.XLOOKUP(B153, ABZ!A:A, ABZ!B:B, "", 0) -> User Interface & Clients | L153: User Interface & Clients
A154: Fapp_adc_20240129-de.xml | B154: JRn | C154: IT | D154: Laura | E154: 123595 | F154: Z:\Produkte\F!Apps\Apps_allgemein\ADC\italienisch\2024.01 | G154: 45320 | H154: 45321 | J154: =_xlfn.XLOOKUP(B154, ABZ!A:A, ABZ!B:B, "", 0) -> User Interface & Clients | L154: User Interface & Clients
A155: Fapp_adc_20240129-de.xml | B155: JRn | C155: NL | D155: Angelique | E155: 123595 | G155: 45320 | H155: 44959 | J155: =_xlfn.XLOOKUP(B155, ABZ!A:A, ABZ!B:B, "", 0) -> User Interface & Clients | L155: User Interface & Clients
...

Sheet 2023
A1: Aufträge | B1: Vom | C1: Sprache | D1: Korrektur | E1: Jazz | F1: Ablageort | G1: Datum | H1: Lieferung | I1: Deadline
A2: 0000_12.998.1.31_translate-from-de | B2: Abromeit | C2: EN | D2: Susan | F2: Z:\Produkte\F!Box allgemein\GUI\deutsch\2022.12 | G2: 44915 | H2: 44936 | I2: 44936
A3: 0000_12.998.1.31_translate-from-de | B3: Abromeit | C3: FR | D3: Martine | F3: Z:\Produkte\F!Box allgemein\GUI\deutsch\2022.12 | G3: 44915 | H3: 44936 | I3: 44936
A4: 0000_12.998.1.31_translate-from-de | B4: Abromeit | C4: IT | D4: Laura | F4: Z:\Produkte\F!Box allgemein\GUI\deutsch\2022.12 | G4: 44915 | H4: 44936 | I4: 44936
A5: 0000_12.998.1.31_translate-from-de | B5: Abromeit | C5: NL | D5: Angelique | F5: Z:\Produkte\F!Box allgemein\GUI\deutsch\2022.12 | G5: 44915 | H5: 44936 | I5: 44936
A6: 0000_12.998.1.31_translate-from-de | B6: Abromeit | C6: ES | D6: Helena | F6: Z:\Produkte\F!Box allgemein\GUI\deutsch\2022.12 | G6: 44915 | H6: 44936 | I6: 44936
A7: 0000_12.998.1.31_translate-from-de-to-pl | B7: Abromeit | C7: PL | D7: Yabylon | F7: Z:\Produkte\F!Box allgemein\GUI\deutsch\2022.12 | G7: 44915 | H7: 44936 | I7: 44936
A8: AVM-Erlebniswelt-de | B8: Luisa | C8: NL | D8: Angelique | G8: 44916 | H8: 44936 | I8: 44936
A9: FappFon_20221222_strings-de | B9: Andre Dossmann | C9: EN | D9: Susan | E9: Entwicklungsauftrag 110394 | F9: Z:\Produkte\F!Apps\FappFon\GUI\Android\deutsch\2022.12 | G9: 44917 | H9: 44936 | I9: 44936
A10: FappFon_20221222_strings-de | C10: IT | D10: Laura | E10: Entwicklungsauftrag 110394 | F10: Z:\Produkte\F!Apps\FappFon\GUI\Android\deutsch\2022.12 | G10: 44917 | H10: 44936 | I10: 44936
A11: Master_Version_13_2023-01-10_D-00000020_T-00000432_EngineeringModules_de-DE_es-ES | B11: doku | C11: ES | D11: Helena | F11: Z:\International\Tico\work\2023-01-10_D-00000020_T-00000432_de-DE_es-ES.xml | G11: 44936 | H11: 44941 | I11: 44941
A12: Master_Version_13_2023-01-10_D-00000020_T-00000434_EngineeringModules_de-DE_nl-NL | B12: doku | C12: NL | D12: Angelique | F12: Z:\International\Tico\work\2023-01-10_D-00000020_T-00000434_de-DE_nl-NL.xml | G12: 44936 | H12: 44945 | I12: 44945
A13: Master_Version_13_2023-01-10_D-00000020_T-00000430_EngineeringModules_de-DE_en-US | B13: doku | C13: US | D13: Susan | F13: Z:\International\Tico\work\2023-01-10_D-00000020_T-00000430_de-DE_en-US.xml | G13: 44936 | H13: 44941 | I13: 44941
A14: Master_Version_13_2023-01-10_D-00000020_T-00000431_EngineeringModules_de-DE_fr-FR | B14: doku | C14: FR | D14: Martine | F14: Z:\International\Tico\work\2023-01-10_D-00000020_T-00000431_de-DE_fr-FR.xml | G14: 44936 | H14: 44941 | I14: 44941
A15: Uebersetzung_BU_Januar_DE-NL | B15: Luisa | C15: NL | D15: Angelique | F15: Z:\Produkte\Texte Web, Marketing, etc\deutsch\2023.01 | G15: 44937 | H15: 44942 | I15: 44942
A16: Produkte hinter login ES_IT_NL | B16: Luisa | C16: ES | D16: Helena | F16: Z:\Produkte\Texte Web, Marketing, etc\deutsch\2023.01 | G16: 44938 | H16: 44946 | I16: 44946
A17: Produkte hinter login ES_IT_NL | B17: Luisa | C17: IT | D17: Laura | F17: Z:\Produkte\Texte Web, Marketing, etc\deutsch\2023.01 | G17: 44938 | H17: 44946 | I17: 44946
A18: Produkte hinter login ES_IT_NL | B18: Luisa | C18: NL | D18: Angelique | F18: Z:\Produkte\Texte Web, Marketing, etc\deutsch\2023.01 | G18: 44938 | H18: 44946 | I18: 44946
A19: Übersetzung Abmeldung CleverReach IT, ES, NL | B19: Luisa | C19: ES | D19: Helena | F19: Z:\Produkte\Texte Web, Marketing, etc\deutsch\2023.01 | G19: 44942 | H19: 44956 | I19: 44956
A20: Übersetzung Abmeldung CleverReach IT, ES, NL | B20: Luisa | C20: IT | D20: Cristina | F20: Z:\Produkte\Texte Web, Marketing, etc\deutsch\2023.01 | G20: 44942 | H20: 44956 | I20: 44956
A21: Übersetzung Abmeldung CleverReach IT, ES, NL | B21: Luisa | C21: NL | D21: Angelique | F21: Z:\Produkte\Texte Web, Marketing, etc\deutsch\2023.01 | G21: 44942 | H21: 44956 | I21: 44956
A22: Übersetzung_DE-NL_IT_ES | B22: Johannes Wiggert | C22: ES | D22: Helena | F22: Z:\Produkte\Texte Web, Marketing, etc\deutsch\2023.01 | G22: 44943 | H22: 44946 | I22: 44946
... A51: translate-from-de-to-pl | B51: Abromeit | C51: PL | D51: Yabylon | F51: Z:\Produkte\F!Box allgemein\GUI\deutsch\2023.02 | G51: 44960 | H51: 44964 | I51: 44964
A52: FappFon_20230201_de-US.xliff | B52: K. Nuding | C52: En | D52: Lisa | E52: Aufgabe 112871 | F52: Z:\Produkte\F!Apps\FappFon\GUI\iOS\englisch\2023.02 | G52: 44966 | H52: 44969 | I52: 44969
A53: FappFon_20230201_de-IT.xliff | B53: K. Nuding | C53: It | D53: Laua | E53: Aufgabe 112871 | F53: Z:\Produkte\F!Apps\FappFon\GUI\iOS\italienisch\2023.02 | G53: 44966 | H53: 44969 | I53: 44969
A54: Broschüre_Projekte mit AVM_gekürzt-de | B54: Christian Oloeslagers | C54: NL | D54: Angelique | F54: Z:\Produkte\Texte Web, Marketing, etc\deutsch\2023.02 | G54: 44966 | H54: 44980 | I54: 44980
A55: Broschüre_Projekte mit AVM_Takko-de | B55: Christian Oloeslagers | C55: NL | D55: Angelique | F55: Z:\Produkte\Texte Web, Marketing, etc\deutsch\2023.02 | G55: 44966 | H55: 44980 | I55: 44980
A56: Master Hilfe Datenschutzerklärung
A57: Master Hilfe Datenschutzerklärung Apps
A58: Changelogs.docx | B58: Felix Hörger, S. Marek | C58: En | D58: Lisa | E58: Aufgabe 110751 | F58: Z:\Produkte\F!Apps\Apps_allgemein | G58: 44971 | H58: 44972 | I58: 44972
A59: Changelogs.docx | B59: Felix Hörger, S. Marek | C59: It | D59: Laura | E59: Aufgabe 110751 | F59: Z:\Produkte\F!Apps\Apps_allgemein | G59: 44971 | H59: 44972 | I59: 44972
A60: FappBoxSetup_20230214_de-US.xliff | B60: K. Krug, S. Marek | D60: Lisa | E60: Story 82740 | F60: Z:\Produkte\F!Apps\FappBoxSetup\englisch\2023.02 | G60: 44974 | H60: 44977 | I60: 44977
A61: FappBoxSetup_20230214_de-IT.xliff | B61: K. Krug, S. Marek | D61: Laura | E61: Story 82740 | F61: Z:\Produkte\F!Apps\FappBoxSetup\italienisch\2023.02 | G61: 44974 | H61: 44977 | I61: 44977
A62: 0000_12-998-1-37_translate-from-de.xml | B62: Abromeit | C62: EN | D62: Susan | F62: Z:\Produkte\F!Box allgemein\GUI\deutsch\2023.02 | G62: 44977 | H62: 44979 | I62: 44979
A63: 0000_12-998-1-37_translate-from-de.xml | B63: Abromeit | C63: IT | D63: Laura | F63: Z:\Produkte\F!Box allgemein\GUI\deutsch\2023.02 | G63: 44977 | H63: 44979 | I63: 44979
A64: 0000_12-998-1-37_translate-from-de.xml | B64: Abromeit | C64: FR | D64: Martine | F64: Z:\Produkte\F!Box allgemein\GUI\deutsch\2023.02 | G64: 44977 | H64: 44979 | I64: 44979
A65: 0000_12-998-1-37_translate-from-de.xml | B65: Abromeit | C65: NL | D65: Angelique | F65: Z:\Produkte\F!Box allgemein\GUI\deutsch\2023.02 | G65: 44977 | H65: 44979 | I65: 44979
A66: 0000_12-998-1-37_translate-from-de.xml | B66: Abromeit | C66: ES | D66: Helena | F66: Z:\Produkte\F!Box allgemein\GUI\deutsch\2023.02 | G66: 44977 | H66: 44979 | I66: 44979
A67: 0000_12-998-1-37_translate-from-de-to-pl.xml | B67: Abromeit | C67: PL | D67: Yabylon | F67: Z:\Produkte\F!Box allgemein\GUI\polnisch\2023.02 | G67: 44977 | H67: 44979 | I67: 44979
A68: infoLab-de.docx | B68: Sylvia Stammberger | C68: En | D68: Susan | F68: Z:\Produkte\F!Box allgemein\Info.txt\22_Move21\2023.02 | G68: 44977 | H68: 44978 | I68: 44978
A69: Script_Fiber final-de | B69: Gordon Priebe | C69: IT | F69: Z:\Produkte\Texte Web, Marketing, etc\deutsch\2023.03 | G69: 44985
A70: Business_Update_NL_Maerz-Ausgabe.docx | B70: Alice Gimmler | C70: Nl | D70: Marion/Angelique | F70: Z:\Produkte\Texte Web, Marketing, etc\deutsch\2023.02 | G70: 44985 | H70: 44992 | I70: 44992
A71: Masters_Hilfe_Version_6_2023-03-01_D-00000051_T-00000440_EngineeringModules_de-DE_en-US | B71: Doku | C71: EN | D71: Susan | F71: Z:\International\Tico\work\2023-03-01_D-00000051_T-00000440_de-DE_en-US.xml | G71: 44986 | H71: 44622 | I71: 44622
A72: Masters_Hilfe_Version_6_2023-03-01_D-00000051_T-00000441_EngineeringModules_de-DE_fr-FR | B72: Doku | C72: FR | D72: Martine | F72: Z:\International\Tico\work\2023-03-01_D-00000051_T-00000441_de-DE_fr-FR.xml | G72: 44986 | H72: 44988 | I72: 44988
A73: Masters_Hilfe_Version_6_2023-03-01_D-00000051_T-00000442_EngineeringModules_de-DE_es-ES | B73: Doku | C73: ES | D73: Helena | F73: Z:\International\Tico\work\2023-03-01_D-00000051_T-00000442_de-DE_es-ES.xml | G73: 44986 | H73: 44622 | I73: 44622
A74: Masters_Hilfe_Version_6_2023-03-01_D-00000051_T-00000443_EngineeringModules_de-DE_it-IT | B74: Doku | C74: it | D74: Laura | F74: Z:\International\Tico\work\2023-03-01_D-00000051_T-00000443_de-DE_it-IT.xml | G74: 44986 | H74: 44994 | I74: 44994
A75: Masters_Hilfe_Version_6_2023-03-01_D-00000051_T-00000444_EngineeringModules_de-DE_nl-NL | B75: Doku | C75: NL | D75: Angelique | F75: Z:\International\Tico\work\2023-03-01_D-00000051_T-00000444_de-DE_nl-NL.xml | G75: 44986 | H75: 44995 | I75: 44995
A76: FappSettings_20230103-de-IT.xliff | B76: A. Zehden | C76: It | D76: Laura | E76: Aufgabe 113823 | F76: Z:\Produkte\F!Apps\Apps_allgemein\Settings\Italienisch\2023.03 | G76: 44988 | H76: 44991 | I76: 44991
A77: FappSettings_20230103-de-US.xliff | B77: A. Zehden | C77: En | D77: Susan | E77: Aufgabe 113823 | F77: Z:\Produkte\F!Apps\Apps_allgemein\Settings\Englisch\2023.03 | G77: 44988 | H77: 44991 | I77: 44991
A78: FAppMyFRITZ_20230303-de-IT.xliff | B78: S. Marek | C78: It | D78: Laura | E78: Aufgabe 113872 | F78: Z:\Produkte\F!Apps\FappMyF\GUI\iOS\italienisch\2023.03 | G78: 44988 | H78: 44991 | I78: 44991
A79: FAppMyFRITZ_20230303-de-US.xliff | B79: S. Marek | C79: En | D79: Susan | E79: Aufgabe 113872 | F79: Z:\Produkte\F!Apps\FappMyF\GUI\iOS\englisch\2023.03 | G79: 44988 | H79: 44991 | I79: 44991
A80: Content_Business_Portal_Premium_Partnerprogramm-de-nl.docx | B80: Alice Gimmler | C80: NL | D80: Angelique | F80: Z:\Produkte\Texte Web, Marketing, etc\deutsch\2023.03 | G80: 44991 | H80: 45000 | I80: 45000
A81: Chili_Bewerbungsprozessmails-de-nl.docx | B81: Alice Gimmler | C81: NL | D81: Angelique | F81: Z:\Produkte\Texte Web, Marketing, etc\deutsch\2023.03 | G81: 44991 | H81: 45000 | I81: 45000
A82: Master_Handbuch_Version 10_2023-03-06_D-00000009_T-00000446_EngineeringModules_de-DE_fr-FR | B82: Doku | C82: FR | D82: Martine | F82: Z:\International\Tico\work\2023-03-06_D-00000009_T-00000446_de-DE_fr-FR.xml | G82: 44991
A83: Master_Handbuch_Version 10_2023-03-06_D-00000009_T-00000447_EngineeringModules_de-DE_es-ES | B83: Doku | C83: ES | D83: Helena | F83: Z:\International\Tico\work\2023-03-06_D-00000009_T-00000447_de-DE_es-ES.xml | G83: 44991 | H83: 44991 | I83: 44991
A84: Master_Handbuch_Version 10_2023-03-06_D-00000009_T-00000448_EngineeringModules_de-DE_it-IT | B84: Doku | C84: IT | D84: Laura | F84: Z:\International\Tico\work\2023-03-06_D-00000009_T-00000448_de-DE_it-IT.xml | G84: 44991
A85: Master_Handbuch_Version 10_2023-03-06_D-00000009_T-00000449_EngineeringModules_de-DE_nl-NL | B85: doku | C85: NL | D85: Angelique | F85: Z:\International\Tico\work\2023-03-06_D-00000009_T-00000449_de-DE_nl-NL.xml | G85: 44991
A86: Master_Handbuch_Version 10_2023-03-06_D-00000009_T-00000445_EngineeringModules_de-DE_en-US | B86: doku | C86: ES | D86: Susan | F86: Z:\International\Tico\work\2023-03-06_D-00000009_T-00000445_de-DE_en-US.xml | G86: 44991
A87: Newsletter_März_DE-IT | B87: Johannes Wiggert | C87: IT | D87: Cristina/Laura | F87: Z:\Produkte\Texte Web, Marketing, etc\deutsch\2023.05 | G87: 44992 | H87: 44999 | I87: 44999
A88: Fapp_adc_20230310_strings-de.xml | B88: Jens Renner | C88: En | D88: Susan | E88: Story 112467 | F88: Z:\Produkte\F!Apps\Apps_allgemein\ADC\deutsch\2023.03 | G88: 44995
B89: Jens Renner | C89: Es | D89: Helena | E89: Story 112467 | F89: Z:\Produkte\F!Apps\Apps_allgemein\ADC\deutsch\2023.05 | G89: 44995 | H89: 45068 | I89: 45068
B90: Jens Renner | C90: Fr | D90: Martine | E90: Story 112467 | F90: Z:\Produkte\F!Apps\Apps_allgemein\ADC\deutsch\2023.05 | G90: 44995 | H90: 45068 | I90: 45068
B91: Jens Renner | C91: It | D91: Laura | E91: Story 112467 | F91: Z:\Produkte\F!Apps\Apps_allgemein\ADC\deutsch\2023.03 | G91: 44995
B92: Jens Renner | C92: Nl | D92: Angelique | E92: Story 112467 | F92: Z:\Produkte\F!Apps\Apps_allgemein\ADC\deutsch\2023.03 | G92: 44995 | H92: 45068 | I92: 45068
B93: Jens Renner | C93: Pl | D93: Yabylon | E93: Story 112467 | F93: Z:\Produkte\F!Apps\Apps_allgemein\ADC\deutsch\2023.03 | G93: 44995
A94: Fapp_analytics_20230120_strings-de.xml | B94: Jens Renner | C94: En | D94: Susan | E94: Story 112467 | F94: Z:\Produkte\F!Apps\Apps_allgemein\Analytics\deutsch\2023.01 | G94: 44991
B95: Jens Renner | C95: Es | D95: Helena | E95: Story 112467 | F95: Z:\Produkte\F!Apps\Apps_allgemein\Analytics\deutsch\2023.05 | G95: 44991 | H95: 45068 | I95: 45068
B96: Jens Renner | C96: Fr | D96: Martine | E96: Story 112467 | F96: Z:\Produkte\F!Apps\Apps_allgemein\Analytics\deutsch\2023.05 | G96: 44991 | H96: 45068 | I96: 45068
B97: Jens Renner | C97: It | D97: Laura | E97: Story 112467 | F97: Z:\Produkte\F!Apps\Apps_allgemein\Analytics\deutsch\2023.01 | G97: 44991
B98: Jens Renner | C98: Nl | D98: Angelique | E98: Story 112467 | F98: Z:\Produkte\F!Apps\Apps_allgemein\Analytics\deutsch\2023.05 | G98: 44991 | H98: 45068 | I98: 45068
B99: Jens Renner | C99: Pl | D99: Yabylon | E99: Story 112467 | F99: Z:\Produkte\F!Apps\Apps_allgemein\Analytics\deutsch\2023.01 | G99: 44991
A100: FappFundamentals_20230120_strings-de.xml | B100: Jens Renner | C100: En | D100: Susan | E100: Story 112467 | F100: Z:\Produkte\F!Apps\Apps_allgemein\Fundamentals\deutsch\2023.03 | G100: 44995
B101: Jens Renner | C101: Es | D101: Helena | E101: Story 112467 | F101: Z:\Produkte\F!Apps\Apps_allgemein\Fundamentals\deutsch\2023.03 | G101: 44995
B102: Jens Renner | C102: Fr | D102: Martine | E102: Story 112467 | F102: Z:\Produkte\F!Apps\Apps_allgemein\Fundamentals\deutsch\2023.03 | G102: 44995
B103: Jens Renner | C103: It | D103: Laura | E103: Story 112467 | F103: Z:\Produkte\F!Apps\Apps_allgemein\Fundamentals\deutsch\2023.03 | G103: 44995
B104: Jens Renner | C104: Nl | D104: Angelique | E104: Story 112467 | F104: Z:\Produkte\F!Apps\Apps_allgemein\Fundamentals\deutsch\2023.03 | G104: 44995
B105: Jens Renner | C105: Pl | D105: Yabylon | E105: Story 112467 | F105: Z:\Produkte\F!Apps\Apps_allgemein\Fundamentals\deutsch\2023.03 | G105: 44995
A106: FappFundamentals_20230309_strings-de.xml | B106: Jens Renner | C106: En | D106: Susan | F106: Z:\Produkte\F!Apps\FappFon\GUI\Android\deutsch\2023.02 | G106: 44991
B107: Jens Renner | C107: Es | D107: Helena | E107: Story 112467 | F107: Z:\Produkte\F!Apps\Apps_allgemein\Fundamentals\deutsch\2023.05 | G107: 44995 | H107: 45068 | I107: 45068
B108: Jens Renner | C108: Fr | D108: Martine | E108: Story 112467 | F108: Z:\Produkte\F!Apps\Apps_allgemein\Fundamentals\deutsch\2023.5 | G108: 44995 | H108: 45068 | I108: 45068
B109: Jens Renner | C109: It | D109: Laura | F109: Z:\Produkte\F!Apps\FappFon\GUI\Android\deutsch\2023.02 | G109: 44991
B110: Jens Renner | C110: Nl | D110: Angelique | E110: Story 112467 | F110: Z:\Produkte\F!Apps\Apps_allgemein\Fundamentals\deutsch\2023.05 | G110: 44995 | H110: 45068 | I110: 45068
B111: Jens Renner | C111: Pl | D111: Yabylon | F111: Z:\Produkte\F!Apps\FappFon\GUI\Android\deutsch\2023.02 | G111: 44991
A112: Master_Version_16_2023-03-10_D-00000020_T-00000454_EngineeringModules_de-DE_nl-NL | B112: Doku | C112: NL | D112: Angelique | F112: Z:\International\Tico\work\2023-03-10_D-00000020_T-00000454_de-DE_nl-NL.xml | G112: 44995 | H112: 45012 | I112: 45012
A113: Master_Version_16_2023-03-10_D-00000020_T-00000452_EngineeringModules_de-DE_es-ES | B113: Doku | C113: es | D113: Helena | F113: Z:\International\Tico\work\2023-03-10_D-00000020_T-00000452_de-DE_es-ES.xml\untranslated | G113: 44995 | H113: 45000 | I113: 45000
A114: Master_Version_16_2023-03-10_D-00000020_T-00000453_EngineeringModules_de-DE_it-IT | B114: Doku | C114: IT | D114: Laura | F114: Z:\International\Tico\work\2023-03-10_D-00000020_T-00000453_de-DE_it-IT.xml | G114: 44995 | H114: 45006 | I114: 45006
A115: Master_Version_16_2023-03-10_D-00000020_T-00000451_EngineeringModules_de-DE_fr-FR | B115: Doku | C115: FR | D115: Martine | F115: Z:\International\Tico\work\2023-03-10_D-00000020_T-00000451_de-DE_fr-FR.xml | G115: 44995 | H115: 45013 | I115: 45013
A116: Master_Version_16_2023-03-10_D-00000020_T-00000450_EngineeringModules_de-DE_en-US | B116: Doku | C116: EN | D116: Susan | F116: Z:\International\Tico\work\2023-03-10_D-00000020_T-00000450_de-DE_en-US.xml | G116: 44995 | H116: 45006 | I116: 45006
A117: 0000_12-998-1-40_translate-from-de.xml | B117: GAb | C117: En | D117: Susan | F117: Z:\Produkte\F!Box allgemein\GUI\englsch\2023.03 | G117: 44998 | H117: 45002 | I117: 45002
C118: Es | D118: Helena | F118: Z:\Produkte\F!Box allgemein\GUI\spanisch\2023.03 | G118: 44998 | H118: 45002 | I118: 45002
C119: Fr | D119: Martine | F119: Z:\Produkte\F!Box allgemein\GUI\französisch\2023.03 | G119: 44998 | H119: 45002 | I119: 45002
C120: It | D120: Laura | F120: Z:\Produkte\F!Box allgemein\GUI\italiensch\2023.03 | G120: 44998 | H120: 45002 | I120: 45002
C121: Nl | D121: Angelique | F121: Z:\Produkte\F!Box allgemein\GUI\niederlaendisch\2023.03 | G121: 44998 | H121: 45002 | I121: 45002
C122: Pl | D122: Yabylon | F122: Z:\Produkte\F!Box allgemein\GUI\polnisch\2023.03 | G122: 44998 | H122: 45002 | I122: 45002
A123: FAppMyFRITZ_20230321-de-IT.xliff | B123: Sebastian Marek | C123: IT | D123: Laura | E123: Aufgabe 114383 | F123: Z:\Produkte\F!Apps\FappMyF\GUI\iOS\italienisch\2023.03 | G123: 45006 | H123: 45008 | I123: 45008
A124: FAppMyFRITZ_20230321-de-US-xliff | B124: Sebastian Marek | C124: EN | D124: Susan | E124: Aufgabe 114383 | F124: Z:\Produkte\F!Apps\FappMyF\GUI\iOS\englisch\2023.03 | G124: 45006 | H124: 45008 | I124: 45008
A125: Changelog iOS WLAN | B125: Sebastian Marek | C125: En + It | D125: Susan + Laura | E125: Aufgabe 113976 | F125: Z:\Produkte\F!Apps\Apps_allgemein | G125: 45013 | H125: 45014 | I125: 45014
A126: Wi-Fi 6 (WLAN AX) kurz erklärt AVM Italia | B126: Johannes Wiggert | C126: it | D126: Cristina/Laura | F126: Z:\Produkte\Texte Web, Marketing, etc\deutsch\2023.03 | G126: 45014 | H126: 45022 | I126: 45022
A127: Premium_Mailing_NL | B127: Alice Gimmler | C127: NL | D127: Angelique | F127: Z:\Produkte\Texte Web, Marketing, etc\deutsch\2023.03 | G127: 45014 | H127: 45019 | I127: 45019
A128: Translations-Newsletter-de | B128: Johannes Wiggert | C128: NL | D128: Angelique | F128: Z:\Produkte\Texte Web, Marketing, etc\deutsch\2023.03 | G128: 45016 | H128: 45027 | I128: 45027
...

Sheet 2022
A1: 2024 | B1: Vom | C1: Sprache | D1: Korrektur | E1: Jazz | F1: Ablageort | G1: Datum | H1: Lieferung | I1: Deadline
A2: GUI Datei | B2: Gunther Abromeit | C2: alle | G2: 44782 | H2: 44802 | I2: 44802
A3: FappWLAN_20220811_strings-de | B3: Sebastian Marek | C3: DE | D3: Eva | G3: 44789 | H3: 44790 | I3: 44790
A4: FAppMyFRITZ_20220816-de | B4: Axel Zehnden | C4: DE | D4: Linda | E4: Aufgabe 107362 | G4: 44789 | H4: 44790 | I4: 44790
A5: FAppMyFRITZ_20220816-en | B5: Axel Zehnden | C5: EN | D5: Susan | E5: Aufgabe 107362 | G5: 44790 | H5: 44795 | I5: 44795
A6: FAppMyFRITZ_20220816-it | B6: Axel Zehnden | C6: IT | E6: Aufgabe 107362 | G6: 44790 | H6: 44796 | I6: 44796
A7: FappSmartHome_20220816-de | B7: Karsten Krug | C7: DE | D7: Linda | E7: Aufgabe 107266 | G7: 44789 | H7: 44789 | I7: 44789
A8: FRITZ!App Smart Home 1.8.7 | B8: Nico Riemer | E8: Story 107472 | G8: 44785 | H8: 44788 | I8: 44788
A9: FRITZ!App Smart Home Android | B9: Nico Riemer | E9: Story 107489 | G9: 44791 | H9: 44795 | I9: 44795
A10: Online Hilfe Master Box | C10: FR | D10: martine | G10: 44791 | H10: 44796 | I10: 44796
A11: Online Hilfe Master Box | C11: EN | D11: Susan | G11: 44791 | H11: 44796 | I11: 44796
A12: Handbuch 3000 AX Korrektur | B12: Linh | C12: FR | D12: Marie | G12: 44795 | H12: 44810 | I12: 44810
A13: Handbuch 3000 AX Korrektur | B13: Linh | C13: EN | D13: Lisa | G13: 44795
A14: Handbuch 3000 AX Korrektur | B14: Linh | C14: IT | D14: Laura? | G14: 44795
A15: Handbuch 3000 AX Korrektur | B15: Linh | C15: ES | D15: Helena | G15: 44795
A16: Handbuch 3000 AX Korrektur | B16: Linh | C16: FR | D16: Marie | G16: 44795 | H16: 44797 | I16: 44797
A17: FappSmartHome_20220822-en | B17: Karsten Krug | C17: EN | D17: Susan | E17: Aufgabe 107266 | G17: 44795 | H17: 44796 | I17: 44796
A18: FappSmartHome_20220822-it | B18: Karsten Krug | C18: IT | D18: Laura | E18: Aufgabe 107266 | G18: 44795 | H18: 44796 | I18: 44796
A19: Lektorat Händler-Newsflash DE | B19: Alice Gimmler | C19: DE | D19: Linda | G19: 44795 | H19: 44796 | I19: 44796
A20: Online Hilfe Master Powerline Version 3 | B20: DOKU | C20: EN | D20: Susan | G20: 44796 | H20: 44796 | I20: 44796
A21: Online Hilfe Master Powerline Version 3 | B21: DOKU | C21: FR | D21: Martine | G21: 44796 | H21: 44797 | I21: 44797
A22: 20220820_LP_Router_Rep_Stick-de | B22: Angelika Paulus | C22: FR | D22: Martine | G22: 44796 | H22: 44802 | I22: 44802
A23: 20220820_LP_Router_Rep_Stick-de | B23: Angelika Paulus | C23: IT | D23: Laura | G23: 44796 | H23: 44803 | I23: 44803
A24: Korrektur Repeater 120AX slo | B24: Mehran Reuter | C24: SLO | D24: Helena | G24: 44796
A25: Übersetzung Booklet DECT 100 int | B25: Daniel | C25: DE | G25: 44796 | H25: 44812 | I25: 44812
A26: Übersetzung Booklet DECT 100 int | C26: EN | D26: Susan | G26: 44796 | H26: 44812 | I26: 44812
A27: Übersetzung Booklet DECT 100 int | C27: IT | D27: Laura | G27: 44796 | H27: 44812 | I27: 44812
A28: Übersetzung Booklet DECT 100 int | C28: FR | D28: Martine | G28: 44796 | H28: 44812 | I28: 44812
A29: Übersetzung Booklet DECT 100 int | C29: ES | D29: Helena | G29: 44796 | H29: 44812 | I29: 44812
A30: Übersetzung Booklet DECT 100 int | C30: NL | D30: Angelique | G30: 44809 | H30: 44811 | I30: 44811
A31: Master_Version_4_2022-08-01_D-00000051_T-00000365_EngineeringModules_de-DE_fr-FR | B31: DOKU | C31: FR | D31: Martine | G31: 44774 | H31: 44797 | I31: 44797
A32: Neuer Übersetzungsauftrag AVM - Onepager - IFA 2022 - EN | B32: Prese | C32: EN | D32: Lisa | G32: 44796 | H32: 44798 | I32: 44798
A33: Neuer Übersetzungsauftrag AVM - Onepager - IFA 2022 - EN | C33: IT | D33: Laura | G33: 44796 | H33: 44799 | I33: 44799
A34: Flexibel mit Mobilfunk-de | B34: Johannes Wiggert | C34: IT | D34: Cristina | G34: 44797 | H34: 44817 | I34: 44817
A35: Flexibel mit Mobilfunk-de | B35: Johannes Wiggert | C35: ES | D35: Helena | G35: 44797 | H35: 44817 | I35: 44817
A36: Flexibel mit Mobilfunk-de | B36: Johannes Wiggert | C36: NL | D36: Angelique | G36: 44797 | H36: 44812 | I36: 44812
A37: AlpArray blickt tief in die Erde-de | B37: Johannes Wiggert | D37: Cristina | H37: 44812 | I37: 44812
A38: AlpArray blickt tief in die Erde-de | B38: Johannes Wiggert | C38: ES | D38: Helena | G38: 44797 | H38: 44812 | I38: 44812
A39: AlpArray blickt tief in die Erde-de | B39: Johannes Wiggert | C39: NL | D39: Angelique | G39: 44797 | H39: 44812 | I39: 44812
A40: iOS Smart Home: Changelog Version 1.6.4 | B40: Michael Rommel | C40: DE | D40: Linda | E40: Aufgabe 105834 | G40: 44797 | H40: 44798 | I40: 44798
A41: iOS Smart Home: Changelog Version 1.6.4 | B41: Michael Rommel | C41: EN | D41: Susan | E41: Aufgabe 105834 | G41: 44797 | H41: 44798 | I41: 44798
A42: iOS Smart Home: Changelog Version 1.6.4 | B42: Michael Rommel | C42: IT | D42: Laura | E42: Aufgabe 105834 | G42: 44797 | H42: 44798 | I42: 44798
A43: info.txt | B43: Sylvia | D43: Linda/Susan | G43: 44799 | H43: 44802 | I43: 44802
A44: Master_Powerline-Hilfe_Version_4 | C44: IT | D44: Laura | G44: 44802 | H44: 44851 | I44: 44851
A45: Master_Box-Hilfe-Version 6 | C45: ES | D45: Helena | G45: 44802 | H45: 44806 | I45: 44806
A46: Master_Box-Hilfe-Version 6 | C46: EN | D46: Susan | G46: 44802 | H46: 44806 | I46: 44806
A47: Master_Box-Hilfe-Version 6 | C47: FR | D47: Marie | G47: 44802 | H47: 44809 | I47: 44809
A48: User-Admin_de | B48: Alice Gimmler | C48: IT | D48: Laura | G48: 44802 | H48: 44804 | I48: 44804
A49: User-Admin_de | B49: Alice Gimmler | C49: ES | D49: Helena | G49: 44802 | H49: 44804 | I49: 44804
A50: IFA Manual | B50: Petra Weigert | C50: EN | D50: Lisa | G50: 44802 | H50: 44802 | I50: 44802
A51: Sicherer Zugriff Firewall und Portfreigaben | B51: Luisa Obeck | C51: NL | D51: Angelique | G51: 44804 | H51: 44833 | I51: 44833
A52: VPN mit FRITZ | B52: Luisa Obeck | C52: NL | D52: Yabylon | G52: 44804 | H52: 44812 | I52: 44812
A53: Sicherer Zugriff Firewall und Portfreigaben | B53: Luisa Obeck | C53: IT | D53: Cristina | G53: 44804 | H53: 44833 | I53: 44833
A54: VPN mit FRITZ | B54: Luisa Obeck | C54: IT | D54: Cristina | G54: 44804 | H54: 44812 | I54: 44812
A55: Sicherer Zugriff Firewall und Portfreigaben | B55: Luisa Obeck | C55: ES | D55: Helena | G55: 44804 | H55: 44833 | I55: 44833
A56: VPN mit FRITZ | B56: Luisa Obeck | C56: Es | D56: Helena | G56: 44804 | H56: 44812 | I56: 44812
A57: Changelog Fon 2.7.0 | B57: Jens Renner | C57: IT | D57: Laura | E57: Entwicklungsauftrag 105301 | G57: 44805 | H57: 44805 | I57: 44805
A58: Changelog Fon 2.7.0 | B58: Jens Renner | C58: EN | D58: Susan | E58: Entwicklungsauftrag 105301 | G58: 44805 | H58: 44805 | I58: 44805
A59: FappSmartHome_20220901-de | B59: Sebastian Marek | C59: DE | D59: Eva | E59: Aufgabe 107746 | G59: 44805 | H59: 44809 | I59: 44809
A60: FappSmartHome_20220901-en | B60: Sebastian Marek | C60: EN | D60: Susan | G60: 44806 | H60: 44809 | I60: 44809
A61: FappSmartHome_20220901-it | B61: Sebastian Marek | C61: IT | D61: Laura | G61: 44806 | H61: 44806 | I61: 44806
A62: Vorlage: FRITZ!POWERLINE 540E WLAN SET International | B62: Daniel | C62: DE | D62: Daniel | G62: 44805
A63: FRITZ!POWERLINE 540E WLAN SET | C63: EN | D63: Susan | G63: 44805 | H63: 44816 | I63: 44816
A64: FRITZ!POWERLINE 540E WLAN SET | C64: FR | D64: Marie | G64: 44805 | H64: 44816 | I64: 44816
A65: FRITZ!POWERLINE 540E WLAN SET | C65: ES | D65: Helena | G65: 44805 | H65: 44816 | I65: 44816
A66: FRITZ!POWERLINE 540E WLAN SET | C66: IT | D66: Laura | G66: 44805 | H66: 44816 | I66: 44816
A67: FRITZ!POWERLINE 540E WLAN SET | C67: NL | D67: Angelique | G67: 44805 | H67: 44816 | I67: 44816
A68: FappFon_20220902_strings-de | B68: Jens Renner | C68: EN | D68: Susan | E68: 105301 | G68: 44806 | H68: 44809 | I68: 44809
A69: FappFon_20220902_strings-de | B69: Jens Renner | C69: IT | D69: Laura | E69: 105301 | G69: 44806 | H69: 44809 | I69: 44809
A70: json (MyFRITZ!)-en | B70: HC-Hablfbrodt | C70: EN | D70: Susan | E70: Aufgabe 108193 | G70: 44809 | H70: 44809 | I70: 44809
A71: json (MyFRITZ!)-fr | C71: FR | D71: Marie | E71: Aufgabe 108193 | G71: 44809 | H71: 44809 | I71: 44809
A72: json (MyFRITZ!)-it | C72: IT | D72: Laura | E72: Aufgabe 108193 | G72: 44809 | H72: 44809 | I72: 44809
A73: json (MyFRITZ!)-nl | C73: NL | D73: Angelique | E73: Aufgabe 108193 | G73: 44809 | H73: 44809 | I73: 44809
A74: json (MyFRITZ!)-es | C74: ES | D74: Helena | E74: Aufgabe 108193 | G74: 44809 | H74: 44809 | I74: 44809
A75: Newsletter NL | B75: Luisa Obeck | C75: NL | D75: Angelique | G75: 44810 | H75: 44820 | I75: 44820
A76: Newsletter ES | B76: Johannes Wiggert | C76: ES | D76: Helena | G76: 44811 | H76: 44817 | I76: 44817
A77: info.txt | B77: Sylvia | C77: EN | D77: Lisa | G77: 44813 | H77: 44818 | I77: 44818
A78: Master_Box-Hilfe-Version 4 | B78: DOKU | C78: NL | D78: Angelique | G78: 44816 | H78: 44832 | I78: 44832
A79: DSL-de | B79: Gordon Priebe | C79: IT | D79: Cristina/Laura | G79: 44817 | H79: 44844 | I79: 44844
A80: Mobilfunk-de | B80: Gordon Priebe | C80: IT | D80: Cristina/Laura | G80: 44817 | H80: 44844 | I80: 44844
A81: MasterRepeater Handbuch v.8 | B81: Doku | C81: NL | D81: Marion/Angelique | G81: 40461 | H81: 44847 | I81: 44847
A82: FappWLAN_20220914_strings-de | B82: E Krysenkova | C82: EN | D82: Susan | E82: Story 108461 | G82: 44818 | H82: 44818 | I82: 44818
A83: FappWLAN_20220914_strings-de | B83: E Krysenkova | C83: IT | D83: Laura | E83: Story 108461 | G83: 44818 | H83: 44818 | I83: 44818
A84: MyFRITZ!App_Storebilder_de | B84: M Rommel | C84: EN | D84: Susan | G84: 44818 | H84: 44818 | I84: 44818
A85: MyFRITZ!App_Storebilder_de | B85: M Rommel | C85: IT | D85: Laura | H85: 44826 | I85: 44826
A86: WLAN Mesh_de-ch | B86: Angelika Paulus | C86: IT | D86: Laura | G86: 44818 | H86: 44818 | I86: 44818
A87: WLAN Mesh_de-ch | B87: Angelika Paulus | C87: FR | D87: Marie | G87: 44818 | H87: 44818 | I87: 44818
A88: Master_Box-Hilfe-Version 7 | B88: DOKU | C88: EN | D88: Susan | G88: 44818 | H88: 44820 | I88: 44820
A89: Master_Box-Hilfe-Version 7 | B89: DOKU | C89: ES | D89: Helena | G89: 44818 | H89: 44820 | I89: 44820
A90: Master_Box-Hilfe-Version 7 | B90: DOKU | C90: FR | D90: Marie | G90: 44818 | H90: 44820 | I90: 44820
A91: Newsletter-De-IT | B91: Johannes Wiggert | C91: IT | D91: Cristina/Laura | G91: 44819 | H91: 44826 | I91: 44826
A92: Awards und Testimonials_DE | B92: Luisa Obeck | C92: NL | D92: Angelique | G92: 44819 | H92: 44833 | I92: 44833
A93: Awards und Testimonials_DE | B93: Luisa Obeck | C93: ES | D93: Helena | G93: 44819 | H93: 44833 | I93: 44833
A94: 20220915_PA_FRITZDECT_302_DE_CH_DE_ | B94: Angelika Paulus | C94: FR | D94: Marie | G94: 44819 | H94: 44827 | I94: 44827
A95: 20220915_PA_FRITZDECT_302_DE_CH_DE_ | B95: Angelika Paulus | C95: IT | D95: Cristtina | G95: 44819 | H95: 44827 | I95: 44827
A96: Master_Box-Hilfe-Version 7 | B96: DOKU | C96: IT | D96: Laura | F96: 2022-09-16_D-00000020_T-00000391_de-DE_it-IT.xml | G96: 44820 | H96: 44855 | I96: 44855
A97: Fehlerliste | B97: Abromeit | G97: 44820 | H97: 44855 | I97: 44855
A98: KA 6890v2 | B98: Daniel | F98: Z:\Produkte\F!Box Kurzanleitungen\international\FRITZ!Box 6890 LTE\2022.05 | G98: 44820
A99: KA 6890v3 | B99: Daniel | D99: Helena | F99: Z:\Produkte\F!Box Kurzanleitungen\international\FRITZ!Box 6890 LTE v3\2022.09 | G99: 44820 | H99: 44823 | I99: 44823
A100: FAppMyFRITZ_20220919-de | B100: Sebastian Marek | C100: DE | D100: Eva | E100: Aufgabe 107953 | G100: 44823 | H100: 44823 | I100: 44823
...
